Temsah/Final_System/System control/SYS_CNTRL.v
module SYS_CNTRL 
#( parameter Data_width = 'd8 , parameter Address_width = 'd4 )
(

//Declaring ingputs
   input wire [ Data_width - 1 : 0 ] ALU_OUT,
   input wire OUT_VALID,
   input wire [ Data_width - 1 : 0 ] RX_p_data,
   input wire RX_d_valid,
   input wire [ Data_width - 1 : 0 ] Rd_data,
   input wire RdData_valid,
   input wire FIFO_full,
   input wire CLK,
   input wire RST,

//Declaring outputs
    output reg ALU_EN,
    output reg [ 3 : 0 ] ALU_FUN,
    output reg  CLK_EN,
    output reg [ Address_width - 1 : 0 ] Address,
    output reg WrEN,
    output reg RdEN,
    output reg [ Data_width - 1 : 0 ] WrData,
    output reg [ Data_width - 1 : 0 ] TX_p_data,
    output reg TX_d_valid,
    output wire clk_div_en

);
/*
//Isolating ALU_OUT , RX_p_data and Rd_data
   input wire [ Data_width - 1 : 0 ] ALU_OUT_isolated,
   input wire [ Data_width - 1 : 0 ] RX_p_data_isolated,
   input wire [ Data_width - 1 : 0 ] Rd_data_isolated,
*/

//FSM encoding
    localparam Idle = 4'b0000;
    localparam Receive_Command = 4'b0001;
    localparam Register_file_address = 4'b0010;
    localparam Register_file_data = 4'b0011;
    localparam Read_operation = 4'b0100;
    localparam Write_operation = 4'b0101;
    localparam ALU_operand_A = 4'b0110;
    localparam ALU_operand_B = 4'b0111;
    localparam ALU_OP_code = 4'b1000;
    localparam ALU_operation = 4'b1001;
    localparam Send_data_TX = 4'b1010;

//Declaring internal registers to store the current and next state 
    reg [ 3 : 0 ] Current_state; 
    reg [ 3 : 0 ] Next_state;

//Declaring internal registers to store the command , data to be written , ALU op code , data to be sent to the tx  and address
    reg [ 7 : 0 ] command;
    /*
    reg [ Data_width - 1 : 0 ] A;
    reg [ Data_width - 1 : 0 ] B;
    */
    reg [ 3 : 0 ] ALU_fun;
    reg [ Address_width - 1 : 0 ] RF_Address;
    reg [ Data_width - 1 : 0 ] RF_Data;
    reg [ Data_width - 1 : 0 ] TX_data;

//making the clock divider enable always equal one 
assign clk_div_en = 1'b1;

//State transition
always@(  posedge CLK  or  negedge RST  )  
    begin
        if( !RST )
            begin
                Current_state <= Idle;
            end
        else        
        Current_state <= Next_state;
    end
//Next state logic
always@( * )
    begin
        case( Current_state )
        Idle:
            begin
                if( RX_d_valid )
                    Next_state = Receive_Command;
                else
                    Next_state = Idle;
            end

        Receive_Command:
            begin
                case( command )  
                8'hAA: Next_state = Register_file_address;
                8'hBB: Next_state = Register_file_address;
                8'hCC: Next_state = ALU_operand_A;
                8'hDD: Next_state = ALU_OP_code;
                default: Next_state = Current_state;
                endcase              
            end

        Register_file_address:
            begin
                if( RX_d_valid )
                    begin
                        if( command == 8'hAA )
                            Next_state = Register_file_data;
                        else if( command == 8'hBB )
                            Next_state = Read_operation;
                        else
                            Next_state = Idle;
                    end
                else 
                    Next_state = Current_state;
            end

        Register_file_data:
            begin
                if( RX_d_valid )
                    Next_state = Write_operation;
                else
                Next_state = Current_state; 
            end

        Read_operation:
            begin
                if( RdData_valid )
                    Next_state = Send_data_TX;
                else
                    Next_state = Current_state;
            end

        Write_operation:
            begin
                Next_state = Send_data_TX;
            end

        ALU_operand_A:
            begin
                if( RX_d_valid )
                    Next_state = ALU_operand_B;
                else 
                    Next_state = Current_state;
            end

        ALU_operand_B:
            begin
                if( RX_d_valid )
                    Next_state = ALU_OP_code;
                else 
                    Next_state = Current_state;
            end

        ALU_OP_code:
            begin
                if( RX_d_valid )
                    Next_state = ALU_operation;
                else 
                    Next_state = Current_state;
            end

        ALU_operation:
            begin
                if( OUT_VALID )
                    Next_state = Send_data_TX;
                else
                    Next_state = Current_state;
            end

        Send_data_TX:
            begin
                Next_state = Idle;
            end

        default : Next_state = Idle;
        endcase
    end


//Output logic 
always@( * )
    begin
//Default values
    ALU_EN = 0;
    //ALU_FUN = 4'b1000;
    CLK_EN = 0;
   // WrEN = 0;
   // RdEN = 0;
    TX_p_data = 0;
    TX_d_valid = 0;

    Address = RF_Address ;
    WrData = RF_Data ;
    ALU_FUN = ALU_fun;
    
    
            case( Current_state )
            Idle:
                begin

                end

            Receive_Command:
                begin    
                    
                    if( RX_d_valid )
                        command = RX_p_data;  
                                      
                end

            Register_file_address:
                begin
                    if( RX_d_valid )
                        RF_Address = RX_p_data [ Address_width - 1 : 0 ]; 
                end

            Register_file_data:
                begin
                    if( RX_d_valid )
                        RF_Data = RX_p_data; 

                end

          //  Read_operation:
               // begin
               //     RdEN = 1;
             //   end

           // Write_operation:
             //   begin
               //     WrEN = 1;
              //      WrData = RF_Data; 
                //end

            ALU_operand_A:
                begin
                    if( RX_d_valid )
                        begin
                            //WrEN = 1;
                            Address = 'd0;
                            WrData = RX_p_data;  
                        end
                end

            ALU_operand_B:
                begin
                    if( RX_d_valid )
                        begin
                            //WrEN = 1;
                            Address = 'd1;
                            WrData = RX_p_data;  
                        end
                end

            ALU_OP_code:
                begin
                    if( RX_d_valid )
                    ALU_fun = RX_p_data[ 3 : 0 ]; 
                end

            ALU_operation:
                begin
                    CLK_EN = 1;
                    ALU_EN = 1;
                    ALU_FUN = ALU_fun;
                end
                
            Send_data_TX:
                begin
                    if( !FIFO_full ) 
                        begin
                        TX_p_data = TX_data;
                        TX_d_valid = 1; 
                        end
                end
            default:
                begin

                end    
            endcase
    end


always@(  posedge CLK  or negedge RST  )
    begin
        if( !RST )
            begin
                RF_Address <= 0;
                RF_Data <= 0;
                ALU_fun <= 0;
                TX_data <= 0;
                command <= 0;
                RdEN <=0;
                WrEN <=0;
            end
        else
            begin
                //Default values
                RdEN<=0;
                WrEN<=0;
                case( Current_state )  
                        Receive_Command: 
                             begin
                               // if( RX_d_valid )
                                  //  command <= RX_p_data;                           
                            end                       
                        Register_file_address:
                            begin
                                if( RX_d_valid )
                                    begin
                                        RF_Address <= RX_p_data[ Address_width - 1 : 0 ];
                                        RF_Data <= 0;  
                                    end                              
                            end                        
                        Register_file_data:
                            begin
                                if( RX_d_valid )
                                    begin
                                        RF_Data <= RX_p_data;  
                                    end                               
                            end                        
                        Read_operation:
                            begin
                                RdEN <=1;
                               // if(RdData_valid) ///////////////////////////////////////
                                TX_data <= Rd_data;                 
                            end                        
                        Write_operation:
                            begin
                                WrEN <=1;
                            end                        

                        ALU_OP_code:
                            begin
                                if( RX_d_valid )
                                    begin
                                        ALU_fun <= RX_p_data; 
                                    end                             
                            end                        
                        ALU_operation:
                            begin
                                if( OUT_VALID )
                                    begin
                                        TX_data <= ALU_OUT;
                                    end                              
                            end                        
                        default: 
                            begin
                              
                            end                        
                                  
                endcase       
            end
    end
endmodule

Temsah/Final_System/System control/SYS_CNTRL_tb.v
`timescale 1ns/1ps
`include "SYS_CNTRL.v"

module SYS_CTRL_TB();

    // Parameters
    parameter Data_width    = 8;
    parameter Address_width = 4;
    parameter CLK_PERIOD    = 20;
    parameter TIMEOUT_CYCLES = 20;

    // Test signals
    reg  [Data_width-1:0] ALU_OUT_tb;
    reg  OUT_VALID_tb;
    reg  [Data_width-1:0] RX_p_data_tb;
    reg  RX_d_valid_tb;
    reg  [Data_width-1:0] Rd_data_tb;
    reg  RdData_valid_tb;
    reg  FIFO_full_tb;
    reg  CLK_tb;
    reg  RST_tb;

    // Outputs
    wire ALU_EN_tb;
    wire [3:0] ALU_FUN_tb;
    wire CLK_EN_tb;
    wire [Address_width-1:0] Address_tb;
    wire WrEN_tb;
    wire RdEN_tb;
    wire [Data_width-1:0] WrData_tb;
    wire [Data_width-1:0] TX_p_data_tb;
    wire TX_d_valid_tb;
    wire clk_div_en_tb;

    integer test_count = 0;
    integer pass_count = 0;
    integer fail_count = 0;

    // DUT
    SYS_CNTRL #(
        .Data_width(Data_width),
        .Address_width(Address_width)
    ) DUT (
        .ALU_OUT(ALU_OUT_tb),
        .OUT_VALID(OUT_VALID_tb),
        .RX_p_data(RX_p_data_tb),
        .RX_d_valid(RX_d_valid_tb),
        .Rd_data(Rd_data_tb),
        .RdData_valid(RdData_valid_tb),
        .FIFO_full(FIFO_full_tb),
        .CLK(CLK_tb),
        .RST(RST_tb),
        .ALU_EN(ALU_EN_tb),
        .ALU_FUN(ALU_FUN_tb),
        .CLK_EN(CLK_EN_tb),
        .Address(Address_tb),
        .WrEN(WrEN_tb),
        .RdEN(RdEN_tb),
        .WrData(WrData_tb),
        .TX_p_data(TX_p_data_tb),
        .TX_d_valid(TX_d_valid_tb),
        .clk_div_en(clk_div_en_tb)
    );

    // Clock
    initial begin
        CLK_tb = 0;
        forever #(CLK_PERIOD/2) CLK_tb = ~CLK_tb;
    end

    // Main sequence
    initial begin
        $dumpfile("ABC.vcd");
        $dumpvars(0, DUT);
        $display("=== SYS_CTRL Testbench ===");

        initialize_signals();
        reset_sequence();

        test_write();
        test_read();
        test_add();
        test_not();

        print_results();
        $finish;
    end

    // ------------------------------------
    // Helpers
    // ------------------------------------
    task initialize_signals;
    begin
        ALU_OUT_tb      = 0;
        OUT_VALID_tb    = 0;
        RX_p_data_tb    = 0;
        RX_d_valid_tb   = 0;
        Rd_data_tb      = 0;
        RdData_valid_tb = 0;
        FIFO_full_tb    = 0;
        RST_tb          = 1;
    end
    endtask

    task reset_sequence;
    begin
        RST_tb = 0;
        #(CLK_PERIOD*2);
        RST_tb = 1;
        #(CLK_PERIOD);
    end
    endtask

    task send_rx_data(input [7:0] data, input [200:0] desc);
    begin
        $display("  Sending %s: 0x%0h", desc, data);
        @(negedge CLK_tb);
        RX_p_data_tb  = data;
        RX_d_valid_tb = 1'b1;
        @(posedge CLK_tb);
        @(negedge CLK_tb);
        RX_d_valid_tb = 1'b0;
    end
    endtask

    task check_signal(input [200:0] name, input [31:0] actual, input [31:0] expected);
    begin
        test_count = test_count + 1;
        if (actual === expected) begin
            $display("  ✓ PASS: %s = 0x%0h", name, actual);
            pass_count = pass_count + 1;
        end else begin
            $display("  ✗ FAIL: %s = 0x%0h (Expected: 0x%0h)", name, actual, expected);
            fail_count = fail_count + 1;
        end
    end
    endtask

    // ------------------------------------
    // Waiters (timeout protected)
    // ------------------------------------
    task wait_for_wren(output integer ok);
        integer i;
    begin
        ok = 0;
        for (i=0; i<TIMEOUT_CYCLES; i=i+1) begin
            @(posedge CLK_tb);
            if (WrEN_tb) begin ok=1; disable wait_for_wren; end
        end
    end
    endtask

    task wait_for_rden(output integer ok);
        integer i;
    begin
        ok = 0;
        for (i=0; i<TIMEOUT_CYCLES; i=i+1) begin
            @(posedge CLK_tb);
            if (RdEN_tb) begin ok=1; disable wait_for_rden; end
        end
    end
    endtask

    task wait_for_alu_en(output integer ok);
        integer i;
    begin
        ok = 0;
        for (i=0; i<TIMEOUT_CYCLES; i=i+1) begin
            @(posedge CLK_tb);
            if (ALU_EN_tb) begin ok=1; disable wait_for_alu_en; end
        end
    end
    endtask

    task wait_for_tx_valid(output integer ok);
        integer i;
    begin
        ok = 0;
        for (i=0; i<TIMEOUT_CYCLES; i=i+1) begin
            @(posedge CLK_tb);
            if (TX_d_valid_tb) begin ok=1; disable wait_for_tx_valid; end
        end
    end
    endtask

    // ------------------------------------
    // Tests
    // ------------------------------------
    task test_write;
        integer ok;
    begin
        $display("\n--- Test 1: Write ---");
        send_rx_data(8'hAA,"Write Command");
        send_rx_data(8'h05,"Address");
        send_rx_data(8'hAB,"Data");

        wait_for_wren(ok);
        if (!ok) $display("  ✗ TIMEOUT WrEN");
        else begin
            check_signal("WrEN",WrEN_tb,1);
            check_signal("Address",Address_tb,4'h5);
            check_signal("WrData",WrData_tb,8'hAB);
        end
    end
    endtask

    task test_read;
        integer ok;
    begin
        $display("\n--- Test 2: Read ---");
        send_rx_data(8'hBB,"Read Command");
        send_rx_data(8'h05,"Address");

        wait_for_rden(ok);
        if (!ok) $display("  ✗ TIMEOUT RdEN");
        else begin
            Rd_data_tb=8'hAB;
            RdData_valid_tb=1; @(posedge CLK_tb); RdData_valid_tb=0;

            wait_for_tx_valid(ok);
            if (!ok) $display("  ✗ TIMEOUT TX");
            else begin
                check_signal("TX_p_data",TX_p_data_tb,8'hAB);
                check_signal("TX_d_valid",TX_d_valid_tb,1);
            end
        end
    end
    endtask

    task test_add;
        integer ok;
    begin
        $display("\n--- Test 3: ALU Add ---");
        send_rx_data(8'hCC,"ALU Command");
        send_rx_data(8'h10,"Operand A");
        send_rx_data(8'h25,"Operand B");
        send_rx_data(8'h00,"FUNC=Add");

        wait_for_alu_en(ok);
        if (!ok) $display("  ✗ TIMEOUT ALU_EN");
        else begin
            @(posedge CLK_tb);
            ALU_OUT_tb=8'h35; OUT_VALID_tb=1;
            @(posedge CLK_tb); OUT_VALID_tb=0;

            wait_for_tx_valid(ok);
            if (!ok) $display("  ✗ TIMEOUT TX");
            else begin
                check_signal("TX_p_data",TX_p_data_tb,8'h35);
                check_signal("TX_d_valid",TX_d_valid_tb,1);
            end
        end
    end
    endtask

    task test_not;
        integer ok;
    begin
        $display("\n--- Test 4: ALU NOT ---");
        send_rx_data(8'hDD,"ALU No-Operand");
        send_rx_data(8'h01,"FUNC=NOT");

        wait_for_alu_en(ok);
        if (!ok) $display("  ✗ TIMEOUT ALU_EN");
        else begin
            @(posedge CLK_tb);
            ALU_OUT_tb=(~8'hAB)&8'hFF; OUT_VALID_tb=1;
            @(posedge CLK_tb); OUT_VALID_tb=0;

            wait_for_tx_valid(ok);
            if (!ok) $display("  ✗ TIMEOUT TX");
            else begin
                check_signal("TX_p_data",TX_p_data_tb,8'h54);
                check_signal("TX_d_valid",TX_d_valid_tb,1);
            end
        end
    end
    endtask

    // ------------------------------------
    // Results
    // ------------------------------------
    task print_results;
    begin
        $display("\n=== Test Results ===");
        $display("Total: %0d  Passed: %0d  Failed: %0d",test_count,pass_count,fail_count);
    end
    endtask

endmodule

Temsah/Final_System/System control/ABC.vcd
$date
	Wed Sep 17 18:48:41 2025
$end
$version
	Icarus Verilog
$end
$timescale
	1ps
$end
$scope module SYS_CTRL_TB $end
$scope module DUT $end
$var wire 8 ! ALU_OUT [7:0] $end
$var wire 1 " CLK $end
$var wire 1 # FIFO_full $end
$var wire 1 $ OUT_VALID $end
$var wire 1 % RST $end
$var wire 1 & RX_d_valid $end
$var wire 8 ' RX_p_data [7:0] $end
$var wire 1 ( RdData_valid $end
$var wire 8 ) Rd_data [7:0] $end
$var wire 1 * clk_div_en $end
$var parameter 4 + ALU_OP_code $end
$var parameter 4 , ALU_operand_A $end
$var parameter 4 - ALU_operand_B $end
$var parameter 4 . ALU_operation $end
$var parameter 32 / Address_width $end
$var parameter 32 0 Data_width $end
$var parameter 4 1 Idle $end
$var parameter 4 2 Read_operation $end
$var parameter 4 3 Receive_Command $end
$var parameter 4 4 Register_file_address $end
$var parameter 4 5 Register_file_data $end
$var parameter 4 6 Send_data_TX $end
$var parameter 4 7 Write_operation $end
$var reg 1 8 ALU_EN $end
$var reg 4 9 ALU_FUN [3:0] $end
$var reg 4 : ALU_fun [3:0] $end
$var reg 4 ; Address [3:0] $end
$var reg 1 < CLK_EN $end
$var reg 4 = Current_state [3:0] $end
$var reg 4 > Next_state [3:0] $end
$var reg 4 ? RF_Address [3:0] $end
$var reg 8 @ RF_Data [7:0] $end
$var reg 1 A RdEN $end
$var reg 1 B TX_d_valid $end
$var reg 8 C TX_data [7:0] $end
$var reg 8 D TX_p_data [7:0] $end
$var reg 8 E WrData [7:0] $end
$var reg 1 F WrEN $end
$var reg 8 G command [7:0] $end
$upscope $end
$upscope $end
$enddefinitions $end
$comment Show the parameter values. $end
$dumpall
b101 7
b1010 6
b11 5
b10 4
b1 3
b100 2
b0 1
b1000 0
b100 /
b1001 .
b111 -
b110 ,
b1000 +
$end
#0
$dumpvars
b0 G
0F
b0 E
b0 D
b0 C
0B
0A
b0 @
b0 ?
b0 >
b0 =
0<
b0 ;
b0 :
b0 9
08
1*
b0 )
0(
b0 '
0&
0%
0$
0#
0"
b0 !
$end
#10000
1"
#20000
0"
#30000
1"
#40000
0"
1%
#50000
1"
#60000
b1 >
1&
b10101010 '
0"
#70000
b10 >
b10101010 G
b1 =
1"
#80000
0&
0"
#90000
b10 =
1"
#100000
b11 >
b101 ?
1&
b101 '
0"
#110000
b101 @
b101 ;
b101 >
b11 =
1"
#120000
b101 E
b11 >
0&
0"
#130000
1"
#140000
b101 >
b10101011 @
1&
b10101011 '
0"
#150000
b10101011 E
b1010 >
b101 =
1"
#160000
0&
0"
#170000
1B
b0 >
1F
b1010 =
1"
#180000
0"
#190000
0B
b0 =
0F
1"
#200000
b1 >
1&
b10111011 '
0"
#210000
b10111011 G
b10 >
b1 =
1"
#220000
0&
0"
#230000
b10 =
1"
#240000
b100 >
1&
b101 '
0"
#250000
b0 E
b0 @
b100 =
1"
#260000
0&
0"
#270000
1A
1"
#280000
0"
#290000
b10101011 C
1A
b1010 >
1(
b10101011 )
1"
#300000
0"
#310000
1B
b10101011 D
b1010 =
1A
b0 >
0(
1"
#320000
0"
#330000
0B
b0 D
0A
b0 =
1"
#340000
b1 >
1&
b11001100 '
0"
#350000
b11001100 G
b110 >
b1 =
1"
#360000
0&
0"
#370000
b110 =
1"
#380000
b111 >
b10000 E
b0 ;
1&
b10000 '
0"
#390000
b10000 E
b1 ;
b1000 >
b111 =
1"
#400000
b0 E
b101 ;
b111 >
0&
0"
#410000
1"
#420000
b1000 >
b100101 E
b1 ;
1&
b100101 '
0"
#430000
b101 :
b0 E
b101 ;
b1001 >
b1000 =
1"
#440000
b101 9
b1000 >
0&
0"
#450000
1"
#460000
b1001 >
b0 :
1&
b0 '
0"
#470000
18
1<
b0 9
b1001 =
1"
#480000
1<
18
0&
0"
#490000
1"
#500000
0"
#510000
1<
18
b110101 C
b1010 >
1$
b110101 !
1"
#520000
0"
#530000
1B
b110101 D
0<
08
b1010 =
b0 >
0$
1"
#540000
0"
#550000
0B
b0 D
b0 =
1"
#560000
b1 >
1&
b11011101 '
0"
#570000
b11011101 G
b1000 >
b1 =
1"
#580000
0&
0"
#590000
b1000 =
1"
#600000
b1001 >
b1 :
1&
b1 '
0"
#610000
18
1<
b1 9
b1001 =
1"
#620000
1<
18
0&
0"
#630000
1"
#640000
0"
#650000
1<
18
b1010100 C
b1010 >
1$
b1010100 !
1"
#660000
0"
#670000
1B
b1010100 D
0<
08
b1010 =
b0 >
0$
1"
#680000
0"
#690000
0B
b0 D
b0 =
1"
