Temsah/Final_System/ALU/MUX.v
module MUX
#( parameter Output_data_width ='d8 )
(
//Declaring inputs
    input wire signed [ Output_data_width - 1 : 0 ] In0,
    input wire signed  [ Output_data_width - 1 : 0 ] In1,
    input wire signed  [ Output_data_width - 1 : 0 ] In2,
    input wire signed [ Output_data_width - 1 : 0 ] In3,
    input wire  [ 1 : 0 ] Sel,
//Declaring outputs
    output reg signed [ Output_data_width - 1 : 0 ] Out
);

always@( * )
    begin
        case( Sel )
            2'b00: Out = In0;
            2'b01: Out = In1;
            2'b10: Out = In2;
            2'b11: Out = In3;
        endcase
    end

endmodule

Temsah/Final_System/Run/SHIFT_UNIT.v
module SHIFT_UNIT#( parameter Input_data_width ='d8 , parameter Output_data_width ='d8  )
(

//Declaring inputs 
    input wire  [ Input_data_width - 1 : 0 ] A,
    input wire  [ Input_data_width - 1 : 0 ] B,
    input wire  [ 1 : 0 ] ALU_FUN,
    input wire CLK,
    input wire RST, //Active low asynchronus reset 
    input wire Shift_Enable,

//Declaring outputs
    output reg  [ Output_data_width - 1 : 0 ] Shift_OUT,
    output reg Shift_Flag

);
//Declaring the op code 
    localparam SHRA=2'b00;   //A>>1
    localparam SHLA=2'b01;  //A<<1
    localparam SHRB=2'b10; //B>>1
    localparam SHLB=2'b11;//B<<1

always@ ( posedge CLK or negedge RST )
    begin
        if( !RST )
            begin

                Shift_OUT <= 0;
                Shift_Flag <= 0;

            end
        else if( Shift_Enable )
                begin
                    case( ALU_FUN )

                        SHRA: Shift_OUT <= A >> 1;
                        SHLA: Shift_OUT <= A << 1;
                        SHRB: Shift_OUT <= B >> 1;
                        SHLB: Shift_OUT <= B << 1;

                    endcase
                        Shift_Flag <= 1'b1;
                end
                else 
                begin

                Shift_OUT <= 0;
                Shift_Flag <= 0;

                end
                    
    end
endmodule

Temsah/Final_System/ALU/CMP_UNIT.v
module CMP_UNIT#( parameter Input_data_width ='d8 , parameter Output_data_width ='d8  )
(

//Declaring inputs 
    input wire  [ Input_data_width - 1 : 0 ] A,
    input wire  [ Input_data_width - 1 : 0 ] B,
    input wire  [ 1 : 0 ] ALU_FUN,
    input wire CLK,
    input wire RST, //Active low asynchronus reset 
    input wire CMP_Enable,

//Declaring outputs
    output reg  [ Output_data_width - 1 : 0 ] CMP_OUT,
    output reg CMP_Flag

);
//Declaring the op code 
    localparam NOP =2'b00;    //no operation
    localparam CMPEQ =2'b01; //checks if A = B
    localparam CMPG =2'b10; //checks if  A > B
    localparam CMPL =2'b11;//Checks if A < B

always@( posedge CLK or negedge RST )
    begin
        if( !RST )
            begin
                CMP_OUT <= 0;
                CMP_Flag <= 0;
            end
        else if( CMP_Enable )
            begin
                case( ALU_FUN )
                    NOP:CMP_OUT <= 0;
                    CMPEQ: if( A == B ) 
                        CMP_OUT <='d1;
                        else
                        CMP_OUT <='d0;
                    CMPG: if( A > B ) 
                        CMP_OUT <='d2;
                        else
                        CMP_OUT <='d0;
                    CMPL: if( A < B ) 
                        CMP_OUT <='d3;
                        else 
                        CMP_OUT <='d0;
                        
                endcase
                        CMP_Flag <='b1;
            end
        else
            begin
                CMP_OUT <=0;
                CMP_Flag <=0;                
            end
    end

endmodule

Temsah/Final_System/Run copy/LOGIC_UNIT.v
module LOGIC_UNIT#( parameter Input_data_width ='d8 , parameter Output_data_width ='d8  )
(

//Declaring inputs 
    input wire  [ Input_data_width - 1 : 0 ] A,
    input wire  [ Input_data_width - 1 : 0 ] B,
    input wire  [ 1 : 0 ] ALU_FUN,
    input wire CLK,
    input wire RST, //Active low asynchronus reset 
    input wire Logic_Enable,

//Declaring outputs
    output reg [ Output_data_width - 1 : 0 ] Logic_OUT,
    output reg Logic_Flag

);
//Declaring the op code 
    localparam AND =2'b00;
    localparam OR =2'b01;
    localparam NAND =2'b10;
    localparam NOR =2'b11;

always@( posedge CLK or negedge RST ) 
    begin
        if( !RST )
            begin
                Logic_OUT <= 0;
                Logic_Flag <= 0;
            end
        else if ( Logic_Enable )
            begin
                case( ALU_FUN )

                AND: Logic_OUT <= A & B ;
                OR: Logic_OUT <= A | B ;
                NAND: Logic_OUT <= ~( A & B ) ;
                NOR: Logic_OUT <= ~( A | B ) ;

                endcase

                     Logic_Flag <= 1'b1;
            end
        else
            begin
                Logic_OUT <= 0;
                Logic_Flag <= 0;
            end 
    
    end
endmodule

Temsah/Final_System/ALU/ARITHMATIC_UNIT.V
module ARITHMATIC_UNIT 
#( parameter Input_data_width ='d8 , parameter Output_data_width ='d8  )
(

//Declaring inputs 
    input wire [ Input_data_width - 1 : 0 ] A,
    input wire [ Input_data_width - 1 : 0 ] B,
    input wire [ 1 : 0 ] ALU_FUN,
    input wire CLK,
    input wire RST, //Active low asynchronus reset 
    input wire Arith_Enable,

//Declaring outputs
    output reg [  Output_data_width - 1 : 0 ] Arith_OUT,
    output reg Arith_Flag

);
//Declaring the op code 
    localparam ADD=2'b00;
    localparam SUB=2'b01;
    localparam MUL=2'b10;
    localparam DIV=2'b11;


always@( posedge CLK or negedge RST )
    begin
            if( !RST )
                begin

                    Arith_OUT<= 0;
                    Arith_Flag <= 1'b0;
                    
                end
            else if( Arith_Enable )
                begin

                     case( ALU_FUN ) 
                       
                            ADD:Arith_OUT <= A + B ;
                            SUB:Arith_OUT <= A - B ;
                            MUL:Arith_OUT <= A * B ; 
                            DIV:Arith_OUT <= A / B ;
                         
                     endcase

                                Arith_Flag <= 1; 
                end
            else
                begin
                    Arith_OUT <= 0;
                    Arith_Flag <= 1'b0;
                end

                
            

    end 

endmodule

Temsah/Final_System/ALU/Decoder.v
module Decoder
(

//Declaring inputs
    input wire [1:0] ALU_FUN,
    input wire ALU_EN,

//Declaring outputs 
    output reg Arith_Enable,
    output reg Logic_Enable,
    output reg CMP_Enable,
    output reg Shift_Enable

);
//Declaring the op code 
    localparam Arith=2'b00; 
    localparam Logic=2'b01;
    localparam CMP=2'b10;
    localparam Shift=2'b11;

always@( * )
    begin
        //Default values
                Arith_Enable=1'b0;
                Logic_Enable=1'b0;
                CMP_Enable=1'b0;
                Shift_Enable=1'b0;
        if( ALU_EN )
        case( ALU_FUN )

            Arith: Arith_Enable=1'b1;
            Logic: Logic_Enable=1'b1;
            CMP: CMP_Enable=1'b1;
            Shift: Shift_Enable=1'b1;
            default:
                begin
                end

        endcase
        else
            begin
                Arith_Enable=1'b0;
                Logic_Enable=1'b0;
                CMP_Enable=1'b0;
                Shift_Enable=1'b0;
            end

    end

endmodule

Temsah/Final_System/ALU/ALU.v
`include "ARITHMATIC_UNIT.v"
`include "LOGIC_UNIT.v"
`include "SHIFT_UNIT.v"
`include "CMP_UNIT.v"
`include "Decoder.v"
`include "MUX.v"
module ALU
#( parameter Input_data_width ='d8 , parameter Output_data_width ='d16  )
(

//Declaring inputs
    input wire [ Input_data_width - 1 : 0 ] A,
    input wire [ Input_data_width - 1 : 0 ] B,
    input wire [ 3 : 0 ] ALU_FUN,
    input wire CLK,
    input wire RST, //Active low asynchronus reset 
    input wire ALU_EN,

//Declaring outputs
    output wire  [ Output_data_width - 1 : 0 ] ALU_OUT,
    output wire OUT_VALID


);
//Declaring internal signals
wire  Arith_Enable_internal;
wire Logic_Enable_internal;
wire Shift_Enable_internal;
wire CMP_Enable_internal;

wire Arith_Flag_internal;
wire Logic_Flag_internal;
wire Shift_Flag_internal;
wire CMP_Flag_internal;

wire signed [ Output_data_width - 1 : 0 ] Arith_out_internal;
wire  [ Output_data_width - 1 : 0 ] Logic_out_internal;
wire  [ Output_data_width - 1 : 0 ] Shift_out_internal;
wire  [ Output_data_width - 1 : 0 ] CMP_out_internal;


//Decoder instantiaton
Decoder D1 
(
.ALU_FUN( ALU_FUN[ 3 : 2 ] ), 
.Arith_Enable( Arith_Enable_internal ),
.Logic_Enable( Logic_Enable_internal ),
.CMP_Enable( CMP_Enable_internal ),
.Shift_Enable( Shift_Enable_internal ),
.ALU_EN( ALU_EN )
);

// Arithmatic unit instantiation
ARITHMATIC_UNIT #( .Input_data_width ( Input_data_width ) , .Output_data_width ( Output_data_width )  ) ARU1 
(
.A( A ),
.B( B ),
.ALU_FUN( ALU_FUN[ 1 : 0 ] ),
.CLK( CLK ),
.RST( RST ),
.Arith_Enable( Arith_Enable_internal ),
.Arith_OUT( Arith_out_internal ),
.Arith_Flag( Arith_Flag_internal )
);

//Logic unit instantiation
LOGIC_UNIT #( .Input_data_width ( Input_data_width ) , .Output_data_width ( Output_data_width ) ) LU1 
(
.A( A ),
.B( B ),
.ALU_FUN (ALU_FUN[ 1 : 0 ]),
.CLK( CLK ),
.RST( RST ),
.Logic_Enable( Logic_Enable_internal ),
.Logic_OUT( Logic_out_internal ),
.Logic_Flag( Logic_Flag_internal )
);

//Compare unit instantiation
CMP_UNIT #( .Input_data_width ( Input_data_width ) , .Output_data_width ( Output_data_width ) ) CMPU1 
( 
.A( A ),
.B( B ),
.ALU_FUN( ALU_FUN[ 1 : 0 ] ),
.CLK( CLK ),
.RST( RST ),
.CMP_Enable( CMP_Enable_internal ),
.CMP_OUT( CMP_out_internal ),
.CMP_Flag( CMP_Flag_internal )
);

//Shift unit instantiation 
SHIFT_UNIT #( .Input_data_width ( Input_data_width ) , .Output_data_width ( Output_data_width ) ) SHU1 
(
.A( A ),
.B( B ),
.ALU_FUN( ALU_FUN[ 1 : 0 ] ),
.CLK( CLK ),
.RST( RST ), 
.Shift_Enable( Shift_Enable_internal ),
.Shift_OUT( Shift_out_internal ),
.Shift_Flag( Shift_Flag_internal )
);

//MUX for ALU_OUT instantiation
MUX #( .Output_data_width ( Output_data_width ) ) ALU_OUT_MUX
(
.In0( Arith_out_internal ),
.In1( Logic_out_internal ),
.In2( CMP_out_internal ),
.In3( Shift_out_internal ),
.Sel( ALU_FUN[ 3 : 2 ] ),
.Out( ALU_OUT )
);

//MUX for OUT_VALID instantiation
MUX #( .Output_data_width ( 1 ) ) OUT_VALID_MUX
(//Declaring inputs
.In0( Arith_Flag_internal ),
.In1( Logic_Flag_internal ),
.In2( CMP_Flag_internal ),
.In3( Shift_Flag_internal ),
.Sel( ALU_FUN[ 3 : 2 ] ),
.Out( OUT_VALID )
);

endmodule

Temsah/Final_System/ALU/ALU_tb.v
`timescale 1ns/1ps
`include "ALU.v"
module ALU_tb;

  // Parameters
  localparam Input_data_width  = 8;
  localparam Output_data_width = 8;

  // Testbench signals
  reg signed [Input_data_width-1:0] A, B;
  reg [3:0] ALU_FUN;
  reg CLK, RST;

  wire signed [Output_data_width-1:0] ALU_OUT;
  wire OUT_VALID;

  // Instantiate DUT
  ALU #(
    .Input_data_width(Input_data_width),
    .Output_data_width(Output_data_width)
  ) DUT (
    .A(A),
    .B(B),
    .ALU_FUN(ALU_FUN),
    .CLK(CLK),
    .RST(RST),
    .ALU_OUT(ALU_OUT),
    .OUT_VALID(OUT_VALID)
  );

  // Clock generation
  initial CLK = 0;
  always #5 CLK = ~CLK; // 100 MHz clock

  // Expected values
  reg signed [Output_data_width-1:0] exp_out;
  reg exp_valid;

  // Task to apply a test with debugging
  task run_test;
    input signed [Input_data_width-1:0] tA;
    input signed [Input_data_width-1:0] tB;
    input [3:0] tFUN;
    input signed [Output_data_width-1:0] expected_out;
    input expected_valid;
    begin
      A = tA;
      B = tB;
      ALU_FUN = tFUN;
      @(posedge CLK); 
      @(posedge CLK); // Wait extra cycle to ensure propagation
      #1; // Small delay for signal settling
      
      exp_out   = expected_out;
      exp_valid = expected_valid;

      // Debug information
      $display("DEBUG: ALU_FUN=%b, [3:2]=%b, [1:0]=%b", ALU_FUN, ALU_FUN[3:2], ALU_FUN[1:0]);
      $display("DEBUG: Enable signals - Arith:%b, Logic:%b, CMP:%b, Shift:%b", 
               DUT.Arith_Enable_internal, DUT.Logic_Enable_internal, 
               DUT.CMP_Enable_internal, DUT.Shift_Enable_internal);
      $display("DEBUG: Unit outputs - Arith:%0d, Logic:%0d, CMP:%0d, Shift:%0d",
               DUT.Arith_out_internal, DUT.Logic_out_internal,
               DUT.CMP_out_internal, DUT.Shift_out_internal);
      $display("DEBUG: Unit flags - Arith:%b, Logic:%b, CMP:%b, Shift:%b",
               DUT.Arith_Flag_internal, DUT.Logic_Flag_internal,
               DUT.CMP_Flag_internal, DUT.Shift_Flag_internal);

      if (ALU_OUT !== exp_out || OUT_VALID !== exp_valid) begin
        $display("ERROR: time=%0t, OP=%b, A=%0d, B=%0d, DUT_OUT=%0d, EXP_OUT=%0d, DUT_VALID=%b, EXP_VALID=%b",
                 $time, ALU_FUN, A, B, ALU_OUT, exp_out, OUT_VALID, exp_valid);
      end else begin
        $display("PASS : time=%0t, OP=%b, A=%0d, B=%0d, OUT=%0d",
                 $time, ALU_FUN, A, B, ALU_OUT);
      end
      $display(""); // Empty line for readability
    end
  endtask

  // Test sequence
  initial begin
    $dumpfile("ALU.vcd");
    $dumpvars;
    $display("==== Starting ALU Testbench ====");

    // Reset
    RST = 0; A = 0; B = 0; ALU_FUN = 4'b0000;
    repeat(3) @(posedge CLK);
    RST = 1;
    repeat(2) @(posedge CLK); // Allow time for reset to propagate

    // Arithmetic (ALU_FUN[3:2] = 00)
    $display("=== ARITHMETIC TESTS ===");
    run_test(10, 5, 4'b0000, 15, 1); // ADD
    run_test(15, 7, 4'b0001, 8, 1);  // SUB

    // Logic (ALU_FUN[3:2] = 01)
    $display("=== LOGIC TESTS ===");
    run_test(8'hF0, 8'h0F, 4'b0100, 8'h00, 1); // AND
    run_test(8'hF0, 8'h0F, 4'b0101, 8'hFF, 1); // OR

    // Compare (ALU_FUN[3:2] = 10)
    $display("=== COMPARE TESTS ===");
    run_test(25, 25, 4'b1001, 1, 1);  // EQ → 1 
    run_test(30, 10, 4'b1010, 2, 1);  // GT → 2 
    run_test(10, 30, 4'b1011, 3, 1);  // LT → 3 

    // Shift (ALU_FUN[3:2] = 11)
    $display("=== SHIFT TESTS ===");
// ALU_FUN = 1100 → A>>1
run_test(8'h0F, 1, 4'b1100, 8'h07, 1); // 0x0F >> 1 = 0x07
// ALU_FUN = 1101 → A<<1
run_test(8'h0F, 1, 4'b1101, 8'h1E, 1); // 0x0F << 1 = 0x1E
// ALU_FUN = 1110 → B>>1
run_test(8'h0F, 4, 4'b1110, 2, 1);     // 4 >> 1 = 2
// ALU_FUN = 1111 → B<<1
run_test(8'h0F, 4, 4'b1111, 8, 1);     // 4 << 1 = 8

    $display("==== Testbench Finished ====");
    $finish;
  end

endmodule

Temsah/Final_System/ALU/ALU.vcd
$date
	Tue Sep 16 17:38:54 2025
$end
$version
	Icarus Verilog
$end
$timescale
	1ps
$end
$scope module ALU_tb $end
$scope module DUT $end
$var wire 8 ! A [7:0] $end
$var wire 1 " ALU_EN $end
$var wire 4 # ALU_FUN [3:0] $end
$var wire 8 $ B [7:0] $end
$var wire 1 % CLK $end
$var wire 1 & RST $end
$var wire 16 ' Shift_out_internal [15:0] $end
$var wire 1 ( Shift_Flag_internal $end
$var wire 1 ) Shift_Enable_internal $end
$var wire 1 * OUT_VALID $end
$var wire 16 + Logic_out_internal [15:0] $end
$var wire 1 , Logic_Flag_internal $end
$var wire 1 - Logic_Enable_internal $end
$var wire 16 . CMP_out_internal [15:0] $end
$var wire 1 / CMP_Flag_internal $end
$var wire 1 0 CMP_Enable_internal $end
$var wire 16 1 Arith_out_internal [15:0] $end
$var wire 1 2 Arith_Flag_internal $end
$var wire 1 3 Arith_Enable_internal $end
$var wire 16 4 ALU_OUT [15:0] $end
$var parameter 32 5 Input_data_width $end
$var parameter 32 6 Output_data_width $end
$scope module ALU_OUT_MUX $end
$var wire 2 7 Sel [1:0] $end
$var wire 16 8 In3 [15:0] $end
$var wire 16 9 In2 [15:0] $end
$var wire 16 : In1 [15:0] $end
$var wire 16 ; In0 [15:0] $end
$var parameter 32 < Output_data_width $end
$var reg 16 = Out [15:0] $end
$upscope $end
$scope module ARU1 $end
$var wire 8 > A [7:0] $end
$var wire 2 ? ALU_FUN [1:0] $end
$var wire 8 @ B [7:0] $end
$var wire 1 % CLK $end
$var wire 1 & RST $end
$var wire 1 3 Arith_Enable $end
$var parameter 2 A ADD $end
$var parameter 2 B DIV $end
$var parameter 32 C Input_data_width $end
$var parameter 2 D MUL $end
$var parameter 32 E Output_data_width $end
$var parameter 2 F SUB $end
$var reg 1 2 Arith_Flag $end
$var reg 16 G Arith_OUT [15:0] $end
$upscope $end
$scope module CMPU1 $end
$var wire 8 H A [7:0] $end
$var wire 2 I ALU_FUN [1:0] $end
$var wire 8 J B [7:0] $end
$var wire 1 % CLK $end
$var wire 1 & RST $end
$var wire 1 0 CMP_Enable $end
$var parameter 2 K CMPEQ $end
$var parameter 2 L CMPG $end
$var parameter 2 M CMPL $end
$var parameter 32 N Input_data_width $end
$var parameter 2 O NOP $end
$var parameter 32 P Output_data_width $end
$var reg 1 / CMP_Flag $end
$var reg 16 Q CMP_OUT [15:0] $end
$upscope $end
$scope module D1 $end
$var wire 1 " ALU_EN $end
$var wire 2 R ALU_FUN [1:0] $end
$var parameter 2 S Arith $end
$var parameter 2 T CMP $end
$var parameter 2 U Logic $end
$var parameter 2 V Shift $end
$var reg 1 3 Arith_Enable $end
$var reg 1 0 CMP_Enable $end
$var reg 1 - Logic_Enable $end
$var reg 1 ) Shift_Enable $end
$upscope $end
$scope module LU1 $end
$var wire 8 W A [7:0] $end
$var wire 2 X ALU_FUN [1:0] $end
$var wire 8 Y B [7:0] $end
$var wire 1 % CLK $end
$var wire 1 - Logic_Enable $end
$var wire 1 & RST $end
$var parameter 2 Z AND $end
$var parameter 32 [ Input_data_width $end
$var parameter 2 \ NAND $end
$var parameter 2 ] NOR $end
$var parameter 2 ^ OR $end
$var parameter 32 _ Output_data_width $end
$var reg 1 , Logic_Flag $end
$var reg 16 ` Logic_OUT [15:0] $end
$upscope $end
$scope module OUT_VALID_MUX $end
$var wire 1 2 In0 $end
$var wire 1 , In1 $end
$var wire 1 / In2 $end
$var wire 2 a Sel [1:0] $end
$var wire 1 ( In3 $end
$var parameter 32 b Output_data_width $end
$var reg 1 * Out $end
$upscope $end
$scope module SHU1 $end
$var wire 8 c A [7:0] $end
$var wire 2 d ALU_FUN [1:0] $end
$var wire 8 e B [7:0] $end
$var wire 1 % CLK $end
$var wire 1 & RST $end
$var wire 1 ) Shift_Enable $end
$var parameter 32 f Input_data_width $end
$var parameter 32 g Output_data_width $end
$var parameter 2 h SHLA $end
$var parameter 2 i SHLB $end
$var parameter 2 j SHRA $end
$var parameter 2 k SHRB $end
$var reg 1 ( Shift_Flag $end
$var reg 16 l Shift_OUT [15:0] $end
$upscope $end
$upscope $end
$upscope $end
$enddefinitions $end
$comment Show the parameter values. $end
$dumpall
b10 k
b0 j
b11 i
b1 h
b10000 g
b1000 f
b1 b
b10000 _
b1 ^
b11 ]
b10 \
b1000 [
b0 Z
b11 V
b1 U
b10 T
b0 S
b10000 P
b0 O
b1000 N
b11 M
b10 L
b1 K
b1 F
b10000 E
b10 D
b1000 C
b11 B
b0 A
b10000 <
b10000 6
b1000 5
$end
#0
$dumpvars
b0 l
b0 e
b0 d
b0 c
b0 a
b0 `
b0 Y
b0 X
b0 W
b0 R
b0 Q
b0 J
b0 I
b0 H
b0 G
b0 @
b0 ?
b0 >
b0 =
b0 ;
b0 :
b0 9
b0 8
b0 7
b0 4
03
02
b0 1
00
0/
b0 .
0-
0,
b0 +
0*
0)
0(
b0 '
0&
0%
b0 $
b0 #
0"
b0 !
$end
#5000
1%
#10000
0%
#15000
1%
#20000
0%
#25000
1&
1%
#30000
0%
#35000
1%
#40000
13
1"
b101 $
b101 @
b101 J
b101 Y
b101 e
b1010 !
b1010 >
b1010 H
b1010 W
b1010 c
0%
#45000
1*
b1111 4
b1111 =
12
b1111 1
b1111 ;
b1111 G
1%
#46000
03
0"
#50000
0%
#55000
0*
b0 4
b0 =
02
b0 1
b0 ;
b0 G
1%
#60000
13
b1 ?
b1 X
b1 I
b1 d
1"
b1 #
b111 $
b111 @
b111 J
b111 Y
b111 e
b1111 !
b1111 >
b1111 H
b1111 W
b1111 c
0%
#65000
1*
b1000 4
b1000 =
12
b1000 1
b1000 ;
b1000 G
1%
#66000
03
0"
#70000
0%
#75000
0*
b0 4
b0 =
02
b0 1
b0 ;
b0 G
1%
#80000
1-
b1 R
b0 ?
b0 X
b0 I
b0 d
b1 7
b1 a
1"
b100 #
b1111 $
b1111 @
b1111 J
b1111 Y
b1111 e
b11110000 !
b11110000 >
b11110000 H
b11110000 W
b11110000 c
0%
#85000
1*
1,
1%
#86000
0-
0"
#90000
0%
#95000
0*
0,
1%
#100000
1-
b1 ?
b1 X
b1 I
b1 d
1"
b101 #
0%
#105000
1*
b11111111 4
b11111111 =
1,
b11111111 +
b11111111 :
b11111111 `
1%
#106000
0-
0"
#110000
0%
#115000
0*
b0 4
b0 =
0,
b0 +
b0 :
b0 `
1%
#120000
10
b10 R
b10 7
b10 a
1"
b1001 #
b11001 $
b11001 @
b11001 J
b11001 Y
b11001 e
b11001 !
b11001 >
b11001 H
b11001 W
b11001 c
0%
#125000
1*
b1 4
b1 =
1/
b1 .
b1 9
b1 Q
1%
#126000
00
0"
#130000
0%
#135000
0*
b0 4
b0 =
0/
b0 .
b0 9
b0 Q
1%
#140000
10
b10 ?
b10 X
b10 I
b10 d
1"
b1010 #
b1010 $
b1010 @
b1010 J
b1010 Y
b1010 e
b11110 !
b11110 >
b11110 H
b11110 W
b11110 c
0%
#145000
1*
b10 4
b10 =
1/
b10 .
b10 9
b10 Q
1%
#146000
00
0"
#150000
0%
#155000
0*
b0 4
b0 =
0/
b0 .
b0 9
b0 Q
1%
#160000
10
b11 ?
b11 X
b11 I
b11 d
1"
b1011 #
b11110 $
b11110 @
b11110 J
b11110 Y
b11110 e
b1010 !
b1010 >
b1010 H
b1010 W
b1010 c
0%
#165000
1*
b11 4
b11 =
1/
b11 .
b11 9
b11 Q
1%
#166000
00
0"
#170000
0%
#175000
0*
b0 4
b0 =
0/
b0 .
b0 9
b0 Q
1%
#180000
1)
b11 R
b0 ?
b0 X
b0 I
b0 d
b11 7
b11 a
1"
b1100 #
b1 $
b1 @
b1 J
b1 Y
b1 e
b1111 !
b1111 >
b1111 H
b1111 W
b1111 c
0%
#185000
1*
b111 4
b111 =
1(
b111 '
b111 8
b111 l
1%
#186000
0)
0"
#190000
0%
#195000
0*
b0 4
b0 =
0(
b0 '
b0 8
b0 l
1%
#200000
1)
b1 ?
b1 X
b1 I
b1 d
1"
b1101 #
0%
#205000
1*
b11110 4
b11110 =
1(
b11110 '
b11110 8
b11110 l
1%
#206000
0)
0"
#210000
0%
#215000
0*
b0 4
b0 =
0(
b0 '
b0 8
b0 l
1%
#220000
1)
b10 ?
b10 X
b10 I
b10 d
1"
b1110 #
b100 $
b100 @
b100 J
b100 Y
b100 e
0%
#225000
1*
b10 4
b10 =
1(
b10 '
b10 8
b10 l
1%
#226000
0)
0"
#230000
0%
#235000
0*
b0 4
b0 =
0(
b0 '
b0 8
b0 l
1%
#240000
1)
b11 ?
b11 X
b11 I
b11 d
1"
b1111 #
0%
#245000
1*
b1000 4
b1000 =
1(
b1000 '
b1000 8
b1000 l
1%
#246000
0)
0"
#250000
0%
#255000
0*
b0 4
b0 =
0(
b0 '
b0 8
b0 l
1%
