Temsah/Assigments/Register_file/Register_file.v
//16x8 register file
module Register_file
(

//Declaring inputs
    input wire [ 15 : 0 ] WrData,
    input wire [ 2 : 0 ] Address,
    input wire WrEn,
    input wire RdEn,
    input wire CLK,
    input wire RST, //Active low asynchronus reset

//Declaring outputs
    output reg [ 15 : 0 ] RdData

);
//Declarint the Register files 
    reg [ 15 : 0 ] Regfile [ 7 : 0 ]; //8 register files everyone of them is 16-bits

always@(posedge CLK or negedge RST )
    begin       
        if(!RST)
            begin
                Regfile[ 7 ] <= 16'b0;
                Regfile[ 6 ] <= 16'b0;
                Regfile[ 5 ] <= 16'b0;
                Regfile[ 4 ] <= 16'b0;
                Regfile[ 3 ] <= 16'b0;
                Regfile[ 2 ] <= 16'b0;
                Regfile[ 1 ] <= 16'b0;
                Regfile[ 0 ] <= 16'b0;
                RdData<=16'b0;
            
            end
        else if ( WrEn && !RdEn )
            begin                    
                    Regfile[ Address ] <= WrData;
            end    
        else if ( RdEn && !WrEn ) 
            begin
                    RdData <= Regfile[ Address ];  
            end  
    end

endmodule

Temsah/Assigments/Register_file/Register_file_tb.v
//Assuming that the frequency is 100KHz
`timescale 1us/1ns
`include "Register_file.v "
module Register_file_tb();

//Declaring the testbench signals

    reg [ 15 : 0 ] WrData_tb;
    reg [ 2 : 0 ] Address_tb;
    reg WrEn_tb;
    reg RdEn_tb;
    reg CLK_tb;
    reg RST_tb;

    wire [ 15 : 0 ] RdData_tb;

Register_file DUT
(  
.WrData( WrData_tb ),
.Address( Address_tb ),
.WrEn( WrEn_tb ),
.RdEn( RdEn_tb ),
.CLK( CLK_tb ),
.RST( RST_tb ),
.RdData( RdData_tb )
);

always #5 CLK_tb = ~CLK_tb;
initial CLK_tb= 1'b0;

initial
begin 

$dumpfile("Register_file.vcd");
$dumpvars;
RST_tb=1'b0;
#10
RST_tb=1'b1;
#10

$display("Test case 1: Writing on register[ 0 ] "); //storing a value 
#10
WrData_tb=16'habcd;
Address_tb=3'b000;
WrEn_tb=1'b1;
RdEn_tb=1'b0;
#10
if( RdData_tb == 16'b0 ) // Value cannot be read because RdEn is low meaning that the read operation is disabled 
    $display("Test case 1 has passed at time %0t", $time );
else
    $display("Test case 1 has failed at time %0t",$time);

$display("Test case 2: Reading from register[ 0 ] "); //checking if the value stored about is stored correclty
#10 
WrEn_tb=1'b0;
RdEn_tb=1'b1;
Address_tb=3'b000;
#10
if( RdData_tb == 16'habcd )
    $display("Test case 2 has passed at time %0t", $time );
else
    $display("Test case 2 has failed at time %0t",$time);

$display("Test case 3: Reading from register[ 5 ] "); //checking if the register file store the values in the intended register 
#10
WrEn_tb=1'b0;
RdEn_tb=1'b1;
Address_tb=3'b101;
#10
if( RdData_tb == 16'b0 )
    $display("Test case 3 has passed at time %0t", $time );
else
    $display("Test case 3 has failed at time %0t",$time);

$display("Test case 4: Testing the Reset ");
#10
Address_tb=3'b000; WrEn_tb=1'b0; RdEn_tb=1'b1;
#10
$display("The value of Register[ 0 ] before resetting is 0x%0h",RdData_tb);
#10
RST_tb=1'b0;
#10
if( RdData_tb == 16'b0 )
begin
    $display("The value of Register[ 0 ] after resetting is 0x%0h", RdData_tb );    
    $display("Test case 4 has passed at time %0t", $time );
end
else
    $display("Test case 4 has failed at time %0t",$time);

$finish;

end

endmodule

Temsah/Assigments/Register_file/Register_file.vcd
$date
	Thu Jul 24 01:52:36 2025
$end
$version
	Icarus Verilog
$end
$timescale
	1ns
$end
$scope module Register_file_tb $end
$var wire 16 ! RdData_tb [15:0] $end
$var reg 3 " Address_tb [2:0] $end
$var reg 1 # CLK_tb $end
$var reg 1 $ RST_tb $end
$var reg 1 % RdEn_tb $end
$var reg 16 & WrData_tb [15:0] $end
$var reg 1 ' WrEn_tb $end
$scope module DUT $end
$var wire 3 ( Address [2:0] $end
$var wire 1 # CLK $end
$var wire 1 $ RST $end
$var wire 1 % RdEn $end
$var wire 16 ) WrData [15:0] $end
$var wire 1 ' WrEn $end
$var reg 16 * RdData [15:0] $end
$upscope $end
$upscope $end
$enddefinitions $end
$comment Show the parameter values. $end
$dumpall
$end
#0
$dumpvars
b0 *
bx )
bx (
x'
bx &
x%
0$
0#
bx "
b0 !
$end
#5000
1#
#10000
0#
1$
#15000
1#
#20000
0#
#25000
1#
#30000
0#
0%
1'
b0 "
b0 (
b1010101111001101 &
b1010101111001101 )
#35000
1#
#40000
0#
#45000
1#
#50000
0#
1%
0'
#55000
b1010101111001101 !
b1010101111001101 *
1#
#60000
0#
#65000
1#
#70000
0#
b101 "
b101 (
#75000
b0 !
b0 *
1#
#80000
0#
#85000
1#
#90000
0#
b0 "
b0 (
#95000
b1010101111001101 !
b1010101111001101 *
1#
#100000
0#
#105000
1#
#110000
b0 !
b0 *
0#
0$
