Temsah/Final_System/Pulse_generator/PULSE_GEN.v
module PULSE_GEN
(
//Declaring inputs
    input wire LVL_SIG,
    input wire CLK,
    input wire RST,

//Declaring output
    output reg PULSE_SIG
);
//Declaring a register to store the previous value of the input signal 
reg PREV;

always@( posedge CLK  or  negedge RST )
    begin
        if( !RST )
            begin
                PREV <= 0;
                PULSE_SIG <= 0;
            end
        else
            begin
                PREV <= LVL_SIG;
                PULSE_SIG <= LVL_SIG && !PREV;
            end
    end

endmodule

Temsah/Final_System/Pulse generator/PULSE_GEN_tb.v
`timescale 1ns/1ps
`include "PULSE_GEN.v"
module tb_PULSE_GEN;

    reg LVL_SIG;
    reg CLK;
    reg RST;
    wire PULSE_SIG;

    // Instantiate DUT
    PULSE_GEN uut (
        .LVL_SIG(LVL_SIG),
        .CLK(CLK),
        .RST(RST),
        .PULSE_SIG(PULSE_SIG)
    );

    // Clock generation: 10ns period
    initial CLK = 0;
    always #5 CLK = ~CLK;

    // Stimulus
    initial begin
        $dumpfile("PULSE_GEN.vcd");
        $dumpvars;
        // Initialize
        RST = 0;
        LVL_SIG = 0;
        #15;       // hold reset for a bit
        RST = 1;

        // Case 1: LVL_SIG goes high for 8 cycles
        #20 LVL_SIG = 1;
        #80 LVL_SIG = 0;

        // Case 2: LVL_SIG goes high for 11 cycles
        #30 LVL_SIG = 1;
        #110 LVL_SIG = 0;

        // Case 3: Quick 2-cycle high pulse
        #40 LVL_SIG = 1;
        #20 LVL_SIG = 0;

        // Case 4: Multiple rising edges
        #30 LVL_SIG = 1;
        #20 LVL_SIG = 0;
        #20 LVL_SIG = 1;
        #20 LVL_SIG = 0;

        // Finish simulation
        #100 $finish;
    end

    // Monitor output
    initial begin
        $monitor("Time=%0t | CLK=%b | RST=%b | LVL_SIG=%b | PULSE_SIG=%b",
                 $time, CLK, RST, LVL_SIG, PULSE_SIG);
    end

endmodule

Temsah/Final_System/Pulse_generator/PULSE_GEN.vcd
$date
	Mon Nov 17 13:11:55 2025
$end
$version
	Icarus Verilog
$end
$timescale
	1ps
$end
$scope module tb_PULSE_GEN $end
$var wire 1 ! PULSE_SIG $end
$var reg 1 " CLK $end
$var reg 1 # LVL_SIG $end
$var reg 1 $ RST $end
$scope module uut $end
$var wire 1 " CLK $end
$var wire 1 # LVL_SIG $end
$var wire 1 $ RST $end
$var reg 1 % PREV $end
$var reg 1 ! PULSE_SIG $end
$upscope $end
$upscope $end
$enddefinitions $end
$comment Show the parameter values. $end
$dumpall
$end
#0
$dumpvars
0%
0$
0#
0"
0!
$end
#5000
1"
#10000
0"
#15000
1"
1$
#20000
0"
#25000
1"
#30000
0"
#35000
1!
1%
1"
1#
#40000
0"
#45000
0!
1"
#50000
0"
#55000
1"
#60000
0"
#65000
1"
#70000
0"
#75000
1"
#80000
0"
#85000
1"
#90000
0"
#95000
1"
#100000
0"
#105000
1"
#110000
0"
#115000
0%
1"
0#
#120000
0"
#125000
1"
#130000
0"
#135000
1"
#140000
0"
#145000
1!
1%
1"
1#
#150000
0"
#155000
0!
1"
#160000
0"
#165000
1"
#170000
0"
#175000
1"
#180000
0"
#185000
1"
#190000
0"
#195000
1"
#200000
0"
#205000
1"
#210000
0"
#215000
1"
#220000
0"
#225000
1"
#230000
0"
#235000
1"
#240000
0"
#245000
1"
#250000
0"
#255000
0%
1"
0#
#260000
0"
#265000
1"
#270000
0"
#275000
1"
#280000
0"
#285000
1"
#290000
0"
#295000
1!
1%
1"
1#
#300000
0"
#305000
0!
1"
#310000
0"
#315000
0%
1"
0#
#320000
0"
#325000
1"
#330000
0"
#335000
1"
#340000
0"
#345000
1!
1%
1"
1#
#350000
0"
#355000
0!
1"
#360000
0"
#365000
0%
1"
0#
#370000
0"
#375000
1"
#380000
0"
#385000
1!
1%
1"
1#
#390000
0"
#395000
0!
1"
#400000
0"
#405000
0%
1"
0#
