Temsah/Final_System/Asyncrhonous_FIFO/BIT_SYNC.v
module BIT_SYNC
#(
    parameter NUM_STAGES = 2,
    parameter BUS_WIDTH = 1
)
(
//Declaring inputs
    input wire [BUS_WIDTH - 1 : 0] ASYNC,
    input wire CLK,
    input wire RST,
//Declaring output
    output reg [BUS_WIDTH - 1 : 0] SYNC
);

//Declaring the synchronizer registers - proper 2D array
reg [NUM_STAGES - 1 : 0] sync_reg [0 : BUS_WIDTH - 1];

//Declaring the loop variable
integer i;

// Initialize to avoid X values
initial begin
    for (i = 0; i < BUS_WIDTH; i = i + 1) begin
        sync_reg[i] = {NUM_STAGES{1'b0}};
    end
    SYNC = {BUS_WIDTH{1'b0}};
end

//Sequential logic for synchronizer flip-flops
always @(posedge CLK or negedge RST) begin
    if (!RST) begin
        for (i = 0; i < BUS_WIDTH; i = i + 1) begin
            sync_reg[i] <= {NUM_STAGES{1'b0}};
        end
    end
    else begin
        for (i = 0; i < BUS_WIDTH; i = i + 1) begin
            sync_reg[i] <= {sync_reg[i][NUM_STAGES - 2 : 0], ASYNC[i]};
        end
    end     
end

//Combinational logic for output
always @(*) begin
    for (i = 0; i < BUS_WIDTH; i = i + 1) begin
        SYNC[i] = sync_reg[i][NUM_STAGES - 1];
    end
end

endmodule

Temsah/Final_System/Folder to be delivered (with temsahs fifo in case yours has  hard latches or whatever)/FIFO_rptr_rempty.v
module FIFO_rptr_rempty #( parameter Address_width = 3 ) //Depth = 2^(Address)
(
//Declaring inputs
    input wire Rinc,
    input wire Rclk,
    input wire Rrst,
    input wire [ Address_width : 0 ] R2q_wptr,
//Declaring outputs
    output wire [ Address_width - 1 : 0 ] Radder,
    output reg Rempty,
    output reg Rempty_flag,
    output reg [ Address_width : 0 ] Rptr
);
//Declaring internal registers
reg [ Address_width  : 0 ] Radder_binary_current;
//reg [ Address_width  : 0 ] Radder_binary_next;
reg [ Address_width : 0 ] Radder_gray_next;

//Rptr logic
    always@( * )
        begin
            Radder_binary_next = Radder_binary_current + ( Rinc & ~Rempty );
            Radder_gray_next = ( Radder_binary_next >> 1 ) ^ Radder_binary_next;
        end
    always@( posedge Rclk  or  negedge Rrst )
        begin
            if( !Rrst ) 
                begin
                    Radder_binary_current <=0;
                    Rptr<=0;
                end
            else  
                begin
                    Radder_binary_current <= Radder_binary_next;
                    Rptr <= Radder_gray_next;
                end      
        end
//Radder logic
assign Radder = Radder_binary_current;

//Rempty logic
always@( posedge Rclk  or  negedge Rrst )
    begin
        if( !Rrst )
            begin
                Rempty <= 1;
            end
        else
            begin
                Rempty <=( Radder_gray_next == R2q_wptr);
                Rempty_flag <=( Radder_gray_next == R2q_wptr);          
            end
    end

endmodule

Temsah/Final_System/Asyncrhonous_FIFO/FIFO_MEMORY.v
module FIFO_MEMORY 
#(
    parameter Data_width = 8,
    parameter Depth = 8,
    parameter Address_width = 3 // depth = 2^(Address) 
)
(
//Declaring write ports
    input wire [ Data_width - 1 : 0 ] Wrdata,
    input wire [ Address_width - 2 : 0 ] Wadder,
    input wire Wclken,
    input wire Wclk,
//Declaring read ports
    output reg [ Data_width - 1 : 0 ] Rdata,
    input wire [ Address_width - 2 : 0 ] Radder,
    input wire Rempty_flag,
    input wire Rclk
);
//Declaring the memory to store the data
 reg [ Data_width - 1 : 0 ] MEM [ Depth - 1 : 0 ];


//Writing
always@( posedge Wclk )
    begin
        if( Wclken )
            MEM[ Wadder ] <= Wrdata ;
    end

//Reading
always@( posedge Rclk )
    begin
        if( !Rempty_flag )
        Rdata <= MEM[ Radder ];
    end

endmodule

Temsah/Final_System/Run copy/Comb_logic.v
module Comb_logic
(
//Declaring inputs
    input wire Winc,
    input wire Wfull,
//Declaring output 
output reg Wclken   
);

always@( * )
    begin
        Wclken = Winc & ~Wfull;
    end

endmodule

Temsah/Final_System/Folder to be delivered (with temsahs fifo in case yours has  hard latches or whatever)/FIFO_wprt_wfull.v
module FIFO_wptr_wfull
#( parameter Address_width = 3 ) // Depth = 2^Address
(
    input  wire           Wrst,
    input  wire           Winc,
    input  wire           Wclk,
    input  wire [Address_width:0] Wq2_rptr, // Read pointer synchronized to write clock

    output wire [Address_width-1:0] Wadder,
    output reg  [Address_width:0]   Wptr,
    output reg                    Wfull
);

    // Internal binary counters
    reg [Address_width:0] Wbin_current, Wbin_next;
    reg [Address_width:0] Wgray_next;

    // Next pointer logic
    always @(*) begin
        Wbin_next  = Wbin_current + (Winc & ~Wfull);
        Wgray_next = (Wbin_next >> 1) ^ Wbin_next; // binary -> Gray
    end

    // Update binary & gray pointer
    always @(posedge Wclk or negedge Wrst) begin
        if (!Wrst) begin
            Wbin_current <= 0;
            Wptr         <= 0;
        end else begin
            Wbin_current <= Wbin_next;
            Wptr         <= Wgray_next;
        end
    end

    assign Wadder = Wbin_current[Address_width-1:0];

    // Synchronize read pointer into write clock domain
    reg [Address_width:0] Rptr_sync1, Rptr_sync2;
    always @(posedge Wclk) begin
        Rptr_sync1 <= Wq2_rptr;
        Rptr_sync2 <= Rptr_sync1;
    end

    // Full detection
    always @(posedge Wclk or negedge Wrst) begin
        if (!Wrst)
            Wfull <= 0;
        else
            Wfull <= (Wgray_next[Address_width]   != Rptr_sync2[Address_width]) &&
                     (Wgray_next[Address_width-1] != Rptr_sync2[Address_width-1]) &&
                     (Wgray_next[Address_width-2:0] == Rptr_sync2[Address_width-2:0]);
    end

endmodule

Temsah/Final_System/Asyncrhonous FIFO/ASYNC_FIFO.v
`include "FIFO_wprt_wfull.v"
`include "Comb_logic.v"
`include "FIFO_MEMORY.v"
`include "FIFO_rptr_rempty.v"
`include "BIT_SYNC.v"
module ASYNC_FIFO
#(  
    parameter Data_width = 8,
    parameter Depth = 8,
    parameter Address_width = 3, // depth = 2^(Address) 
    parameter NUM_STAGES= 2
)
(
//Declaring inputs
    input wire Winc,
    input wire Wrst,
    input wire Wclk,
    input wire Rinc,
    input wire Rrst,
    input wire Rclk,
    input wire [ Data_width - 1 : 0 ] Wrdata,
//Declaring outputs
    output wire Wfull,
    output wire Rempty,
    output wire [ Data_width - 1 : 0 ] Rdata
);
//Internal signals
wire [ Address_width : 0 ] Wq2_rptr_internal;
wire [ Address_width - 1 : 0 ] Wadder_internal;
wire [ Address_width : 0 ] Wptr_internal;
wire Wclken_internal;
wire [ Address_width - 1 : 0 ] Radder_internal;
wire [ Address_width : 0 ]R2q_wptr_internal;
wire [ Address_width : 0 ] Rptr_internal;
wire Rempty_flag_internal;


//Modules instantiation

FIFO_wptr_wfull 
#( .Address_width ( Address_width ) )
FIFO_WPTRFULL
(
.Wrst( Wrst ),
.Winc( Winc ),
.Wclk( Wclk ),
.Wq2_rptr( Wq2_rptr_internal ),
.Wadder( Wadder_internal ),
.Wptr( Wptr_internal ),
.Wfull( Wfull )
);

Comb_logic Clogic 
(
.Winc( Winc ),
.Wfull( Wfull ),
.Wclken( Wclken_internal )    
);

FIFO_MEMORY
#(
.Data_width ( Data_width ),
.Depth ( Depth ),
.Address_width ( Address_width )
)
FIFO_MEM
(
.Wrdata( Wrdata ),
.Wadder( Wadder_internal ),
.Wclken( Wclken_internal ),
.Wclk( Wclk ),
.Rdata( Rdata ),
.Radder( Radder_internal ),
.Rclk( Rclk ),
.Rempty_flag( Rempty_flag_internal )
);

FIFO_rptr_rempty
#( .Address_width ( Address_width ) )
FIFO_RPTRREMPTY
(
.Rinc( Rinc ),
.Rclk( Rclk ),
.Rrst( Rrst ),
.R2q_wptr( R2q_wptr_internal ),
.Radder( Radder_internal ),
.Rempty( Rempty ),
.Rptr( Rptr_internal ),
.Rempty_flag( Rempty_flag_internal )
);

BIT_SYNC 
#(
.NUM_STAGES( NUM_STAGES ),
.BUS_WIDTH ( Address_width + 1 )
)
BIT_W2q_rptr
(
.ASYNC( Rptr_internal ),
.CLK( Wclk ),
.RST( Wrst ),
.SYNC( Wq2_rptr_internal )
);

BIT_SYNC 
#(
.NUM_STAGES( NUM_STAGES ),
.BUS_WIDTH ( Address_width + 1 )
)
BIT_r2q_wptr
(
.ASYNC( Wptr_internal ),
.CLK( Rclk ),
.RST( Rrst ),
.SYNC( R2q_wptr_internal )
);

endmodule

Temsah/Final_System/Folder to be delivered (with temsahs fifo in case yours has  hard latches or whatever)/ASYNC_FIFO_tb.v
`include "ASYNC_FIFO.v"
`timescale 1ns/1ps
module ASYNC_FIFO_tb();
//Declaring the read and write clock periods
  parameter Wperiod = 10 ;
  parameter Rperiod =25 ;
//Declaring the parameters
    parameter Data_width = 8;
    parameter Depth = 8;
    parameter Address_width = 3; // depth = 2^(Address) 
    parameter NUM_STAGES= 2;
//Declaring the testbench signals
    reg Winc_tb;
    reg Wrst_tb;
    reg Wclk_tb;
    reg Rinc_tb;
    reg Rrst_tb;
    reg Rclk_tb;
    reg [ Data_width - 1 : 0 ] Wrdata_tb;
    wire Wfull_tb;
    wire Rempty_tb;
    wire [Data_width - 1 : 0 ] Rdata_tb;
//Declaring the loop variabe
    integer i;
    integer Windex; //write index to know how many elements have been written
    integer Rindex; //read index to know how many elements have been read
//Declaring an internal memory to stored the expected output at
    reg [ Data_width - 1 : 0 ] expected_output [ Depth - 1 : 0 ];
//Delcaring a done flag that equals one when a cetain task is done
    reg done=0;

//Clock generation
always //Write clock 
  begin
    Wclk_tb=0;
    #( Wperiod/2.0 );
    Wclk_tb=1;
    #( Wperiod/2.0 );
  end
  always //Read clock
  begin
    Rclk_tb=0;
    #( Rperiod/2.0 );
    Rclk_tb=1;
    #( Rperiod/2.0 );
  end


//Tasks
task initialize();
  begin
    Winc_tb = 0;
    Wrst_tb = 1;
    Rinc_tb = 0;
    Rrst_tb = 1;
    Wrdata_tb = 0;
  end
endtask

task reset();
  begin
    Wrst_tb = 0;
    Rrst_tb = 0;
    @( posedge Rclk_tb );
    Wrst_tb = 1;
    Rrst_tb = 1;
    @( posedge Rclk_tb );
    Windex = 0;
    Rindex = 0;   
  end
endtask

task write ( input [ Data_width - 1 : 0 ] data );
  begin
    @( posedge Wclk_tb )
    if( !Wfull_tb )
      begin
        Wrdata_tb = data;
        expected_output[ Windex ] = data;
        Windex = Windex + 1;
        Winc_tb = 1;
        @( posedge Wclk_tb )
        Winc_tb =0;

      end 
  end
endtask

task read();
  begin
    @( posedge Rclk_tb )
    if( !Rempty_tb )
      begin
        Rinc_tb = 1;
        @(posedge Rclk_tb)
        Rinc_tb = 0;     
      if( Rdata_tb != expected_output[ Rindex ] )
      begin
        $display("There is an error with reading the data");
      end   
      Rindex = Rindex + 1;     
      end

  end
endtask

//Write initial block
initial 
  begin
    $dumpfile("ASYNC_FIFO.vcd");
    $dumpvars;
    initialize();
    reset();

      $display("Test case 1: trying to fill FIFO to its maximum value");
        for(  i = 1  ;  i <= Depth  ; i = i + 1  )
          begin
            write( 'd10 + i );
          end
          #( Wclk_tb );
          $display("Number of writes=%0d ,Wfull=%0b , Wempty=%0b", Windex , Wfull_tb , Rempty_tb );

    $display("Test case 2 : trying to store a data when the FIFO is full");
        write( 'd10 + 10 );
        #( Wclk_tb );
        $display("Wfull=%0b , Wempty=%0b", Wfull_tb , Rempty_tb );


  end

//Read initial block
initial
  begin
    #300;
    $display("Test case 3: trying to read all the contents in the FIFO ");
          while( !Rempty_tb  && (Rindex < Windex) ) 
            read();
            #( Rclk_tb );
            $display("Number of Reads=%0d ,Wfull=%0b , Wempty=%0b", Rindex , Wfull_tb , Rempty_tb );



    $display("Test case 4: trying to read when the FIFO is empty");
          read();
          #( Rclk_tb );
          $display("Wfull=%0b , Wempty=%0b", Wfull_tb , Rempty_tb );



    $display("Test case 5: trying to read and write simultaneously");
        reset();
          done=0;
        fork
          begin
            for(  i = 1  ;  i <= Depth   ; i = i + 1 )
              write( 'd50 + i );
          end
          begin
            while( !done )
              begin
                read();
                if( Rindex == Depth)
                done = 1 ;
                else
                read();
              end
          end
        join
        @( posedge Rclk_tb )
        $display("Number of Reads=%0d , Number of writes=%0d , Wfull=%0b , Wempty=%0b", Rindex , Windex , Wfull_tb , Rempty_tb );   

    #100 ;
    $finish;
  end


//Module instantiation
ASYNC_FIFO
#(
.Data_width( Data_width ),
.Depth( Depth ),
 .Address_width ( Address_width ), 
.NUM_STAGES( NUM_STAGES )
)
FIFOASYNC
(
.Winc( Winc_tb ),
.Wrst( Wrst_tb ),
.Wclk( Wclk_tb ),
.Rinc( Rinc_tb ),
.Rrst( Rrst_tb ),
.Rclk( Rclk_tb ),
.Wrdata( Wrdata_tb ),
.Wfull( Wfull_tb ),
.Rempty( Rempty_tb ),
.Rdata( Rdata_tb )
);

endmodule

Temsah/Final_System/Folder to be delivered (with temsahs fifo in case yours has  hard latches or whatever)/ASYNC_FIFO.vcd
$date
	Fri Sep 19 17:19:29 2025
$end
$version
	Icarus Verilog
$end
$timescale
	1ps
$end
$scope module ASYNC_FIFO_tb $end
$var wire 1 ! Wfull_tb $end
$var wire 1 " Rempty_tb $end
$var wire 8 # Rdata_tb [7:0] $end
$var parameter 32 $ Address_width $end
$var parameter 32 % Data_width $end
$var parameter 32 & Depth $end
$var parameter 32 ' NUM_STAGES $end
$var parameter 32 ( Rperiod $end
$var parameter 32 ) Wperiod $end
$var reg 1 * Rclk_tb $end
$var reg 1 + Rinc_tb $end
$var reg 1 , Rrst_tb $end
$var reg 1 - Wclk_tb $end
$var reg 1 . Winc_tb $end
$var reg 8 / Wrdata_tb [7:0] $end
$var reg 1 0 Wrst_tb $end
$var reg 1 1 done $end
$var integer 32 2 Rindex [31:0] $end
$var integer 32 3 Windex [31:0] $end
$var integer 32 4 i [31:0] $end
$scope module FIFOASYNC $end
$var wire 1 * Rclk $end
$var wire 1 + Rinc $end
$var wire 1 , Rrst $end
$var wire 1 - Wclk $end
$var wire 1 . Winc $end
$var wire 8 5 Wrdata [7:0] $end
$var wire 1 0 Wrst $end
$var wire 4 6 Wq2_rptr_internal [3:0] $end
$var wire 4 7 Wptr_internal [3:0] $end
$var wire 1 ! Wfull $end
$var wire 1 8 Wclken_internal $end
$var wire 3 9 Wadder_internal [2:0] $end
$var wire 4 : Rptr_internal [3:0] $end
$var wire 1 ; Rempty_flag_internal $end
$var wire 1 " Rempty $end
$var wire 8 < Rdata [7:0] $end
$var wire 3 = Radder_internal [2:0] $end
$var wire 4 > R2q_wptr_internal [3:0] $end
$var parameter 32 ? Address_width $end
$var parameter 32 @ Data_width $end
$var parameter 32 A Depth $end
$var parameter 32 B NUM_STAGES $end
$scope module BIT_W2q_rptr $end
$var wire 1 - CLK $end
$var wire 1 0 RST $end
$var wire 4 C ASYNC [3:0] $end
$var parameter 33 D BUS_WIDTH $end
$var parameter 32 E NUM_STAGES $end
$var reg 4 F SYNC [3:0] $end
$var integer 32 G i [31:0] $end
$upscope $end
$scope module BIT_r2q_wptr $end
$var wire 1 * CLK $end
$var wire 1 , RST $end
$var wire 4 H ASYNC [3:0] $end
$var parameter 33 I BUS_WIDTH $end
$var parameter 32 J NUM_STAGES $end
$var reg 4 K SYNC [3:0] $end
$var integer 32 L i [31:0] $end
$upscope $end
$scope module Clogic $end
$var wire 1 . Winc $end
$var wire 1 ! Wfull $end
$var reg 1 8 Wclken $end
$upscope $end
$scope module FIFO_MEM $end
$var wire 1 * Rclk $end
$var wire 1 - Wclk $end
$var wire 1 8 Wclken $end
$var wire 8 M Wrdata [7:0] $end
$var wire 3 N Wadder [2:0] $end
$var wire 1 ; Rempty_flag $end
$var wire 3 O Radder [2:0] $end
$var parameter 32 P Address_width $end
$var parameter 32 Q Data_width $end
$var parameter 32 R Depth $end
$var reg 8 S Rdata [7:0] $end
$upscope $end
$scope module FIFO_RPTRREMPTY $end
$var wire 4 T R2q_wptr [3:0] $end
$var wire 1 * Rclk $end
$var wire 1 + Rinc $end
$var wire 1 , Rrst $end
$var wire 3 U Radder [2:0] $end
$var parameter 32 V Address_width $end
$var reg 4 W Radder_binary_current [3:0] $end
$var reg 4 X Radder_binary_next [3:0] $end
$var reg 4 Y Radder_gray_next [3:0] $end
$var reg 1 " Rempty $end
$var reg 1 ; Rempty_flag $end
$var reg 4 Z Rptr [3:0] $end
$upscope $end
$scope module FIFO_WPTRFULL $end
$var wire 1 - Wclk $end
$var wire 1 . Winc $end
$var wire 4 [ Wq2_rptr [3:0] $end
$var wire 1 0 Wrst $end
$var wire 3 \ Wadder [2:0] $end
$var parameter 32 ] Address_width $end
$var reg 4 ^ Rptr_sync1 [3:0] $end
$var reg 4 _ Rptr_sync2 [3:0] $end
$var reg 4 ` Wbin_current [3:0] $end
$var reg 4 a Wbin_next [3:0] $end
$var reg 1 ! Wfull $end
$var reg 4 b Wgray_next [3:0] $end
$var reg 4 c Wptr [3:0] $end
$upscope $end
$upscope $end
$scope task initialize $end
$upscope $end
$scope task read $end
$upscope $end
$scope task reset $end
$upscope $end
$scope task write $end
$var reg 8 d data [7:0] $end
$upscope $end
$upscope $end
$enddefinitions $end
$comment Show the parameter values. $end
$dumpall
b11 ]
b11 V
b1000 R
b1000 Q
b11 P
b10 J
b100 I
b10 E
b100 D
b10 B
b1000 A
b1000 @
b11 ?
b1010 )
b11001 (
b10 '
b1000 &
b1000 %
b11 $
$end
#0
$dumpvars
bx d
b0 c
b0 b
b0 a
b0 `
bx _
bx ^
b0 \
b0 [
b0 Z
b0 Y
b0 X
b0 W
b0 U
b0 T
bx S
b0 O
b0 N
b0 M
b100 L
b0 K
b0 H
b100 G
b0 F
b0 C
b0 >
b0 =
bx <
x;
b0 :
b0 9
08
b0 7
b0 6
b0 5
bx 4
bx 3
bx 2
01
00
b0 /
0.
0-
0,
0+
0*
bx #
1"
0!
$end
#5000
b0 ^
b100 G
1-
#10000
0-
#12500
1;
b100 L
1,
10
1*
#15000
x!
b0 _
b100 G
1-
#20000
0-
#25000
0!
b100 G
1-
0*
#30000
0-
#35000
b100 G
1-
#37500
b100 L
b1011 d
b1 4
b0 2
b0 3
1*
#40000
0-
#45000
18
b1 b
b1 a
b100 G
1.
b1 3
b1011 /
b1011 5
b1011 M
1-
#50000
0-
0*
#55000
b1 9
b1 N
b1 \
b1 7
b1 H
b1 c
b1 `
08
b1 b
b1 a
b100 G
b1100 d
b10 4
0.
1-
#60000
0-
#62500
b100 L
1*
#65000
18
b11 b
b10 a
b100 G
1.
b10 3
b1100 /
b1100 5
b1100 M
1-
#70000
0-
#75000
b10 9
b10 N
b10 \
b11 7
b11 H
b11 c
b10 `
08
b11 b
b10 a
b100 G
b1101 d
b11 4
0.
1-
0*
#80000
0-
#85000
18
b10 b
b11 a
b100 G
1.
b11 3
b1101 /
b1101 5
b1101 M
1-
#87500
b1 >
b1 K
b1 T
b100 L
1*
#90000
0-
#95000
b11 9
b11 N
b11 \
b10 7
b10 H
b10 c
b11 `
08
b10 b
b11 a
b100 G
b1110 d
b100 4
0.
1-
#100000
0-
0*
#105000
18
b110 b
b100 a
b100 G
1.
b100 3
b1110 /
b1110 5
b1110 M
1-
#110000
0-
#112500
b11 >
b11 K
b11 T
0;
0"
b100 L
1*
#115000
b100 9
b100 N
b100 \
b110 7
b110 H
b110 c
b100 `
08
b110 b
b100 a
b100 G
b1111 d
b101 4
0.
1-
#120000
0-
#125000
18
b111 b
b101 a
b100 G
1.
b101 3
b1111 /
b1111 5
b1111 M
1-
0*
#130000
0-
#135000
b101 9
b101 N
b101 \
b111 7
b111 H
b111 c
b101 `
08
b111 b
b101 a
b100 G
b10000 d
b110 4
0.
1-
#137500
b10 >
b10 K
b10 T
b1011 #
b1011 <
b1011 S
b100 L
1*
#140000
0-
#145000
18
b101 b
b110 a
b100 G
1.
b110 3
b10000 /
b10000 5
b10000 M
1-
#150000
0-
0*
#155000
b110 9
b110 N
b110 \
b101 7
b101 H
b101 c
b110 `
08
b101 b
b110 a
b100 G
b10001 d
b111 4
0.
1-
#160000
0-
#162500
b111 >
b111 K
b111 T
b100 L
1*
#165000
18
b100 b
b111 a
b100 G
1.
b111 3
b10001 /
b10001 5
b10001 M
1-
#170000
0-
#175000
b111 9
b111 N
b111 \
b100 7
b100 H
b100 c
b111 `
08
b100 b
b111 a
b100 G
b10010 d
b1000 4
0.
1-
0*
#180000
0-
#185000
18
b1100 b
b1000 a
b100 G
1.
b1000 3
b10010 /
b10010 5
b10010 M
1-
#187500
b101 >
b101 K
b101 T
b100 L
1*
#190000
0-
#195000
b0 9
b0 N
b0 \
b1100 7
b1100 H
b1100 c
b1000 `
1!
08
b1100 b
b1000 a
b100 G
b1001 4
0.
1-
#196000
b10100 d
#200000
0-
0*
#205000
b100 G
1-
#210000
0-
#212500
b100 >
b100 K
b100 T
b100 L
1*
#215000
b100 G
1-
#220000
0-
#225000
b100 G
1-
0*
#230000
0-
#235000
b100 G
1-
#237500
b1100 >
b1100 K
b1100 T
b100 L
1*
#240000
0-
#245000
b100 G
1-
#250000
0-
0*
#255000
b100 G
1-
#260000
0-
#262500
b100 L
1*
#265000
b100 G
1-
#270000
0-
#275000
b100 G
1-
0*
#280000
0-
#285000
b100 G
1-
#287500
b100 L
1*
#290000
0-
#295000
b100 G
1-
#300000
0-
0*
#305000
b100 G
1-
#310000
0-
#312500
b1 Y
b1 X
b100 L
1+
1*
#315000
b100 G
1-
#320000
0-
#325000
b100 G
1-
0*
#330000
0-
#335000
b100 G
1-
#337500
b1 =
b1 O
b1 U
b1 :
b1 C
b1 Z
b1 W
b1 Y
b1 X
b100 L
b1 2
0+
1*
#340000
0-
#345000
b100 G
1-
#350000
0-
0*
#355000
b1 6
b1 F
b1 [
b100 G
1-
#360000
0-
#362500
b1100 #
b1100 <
b1100 S
b11 Y
b10 X
b100 L
1+
1*
#365000
b1 ^
b100 G
1-
#370000
0-
#375000
b1 _
b100 G
1-
0*
#380000
0-
#385000
0!
b100 G
1-
#387500
b10 =
b10 O
b10 U
b11 :
b11 C
b11 Z
b10 W
b11 Y
b10 X
b100 L
b10 2
0+
1*
#390000
0-
#395000
b100 G
1-
#400000
0-
0*
#405000
b11 6
b11 F
b11 [
b100 G
1-
#410000
0-
#412500
b1101 #
b1101 <
b1101 S
b10 Y
b11 X
b100 L
1+
1*
#415000
b11 ^
b100 G
1-
#420000
0-
#425000
b11 _
b100 G
1-
0*
#430000
0-
#435000
b100 G
1-
#437500
b11 =
b11 O
b11 U
b10 :
b10 C
b10 Z
b11 W
b10 Y
b11 X
b100 L
b11 2
0+
1*
#440000
0-
#445000
b100 G
1-
#450000
0-
0*
#455000
b10 6
b10 F
b10 [
b100 G
1-
#460000
0-
#462500
b1110 #
b1110 <
b1110 S
b110 Y
b100 X
b100 L
1+
1*
#465000
b10 ^
b100 G
1-
#470000
0-
#475000
b10 _
b100 G
1-
0*
#480000
0-
#485000
b100 G
1-
#487500
b100 =
b100 O
b100 U
b110 :
b110 C
b110 Z
b100 W
b110 Y
b100 X
b100 L
b100 2
0+
1*
#490000
0-
#495000
b100 G
1-
#500000
0-
0*
#505000
b110 6
b110 F
b110 [
b100 G
1-
#510000
0-
#512500
b1111 #
b1111 <
b1111 S
b111 Y
b101 X
b100 L
1+
1*
#515000
b110 ^
b100 G
1-
#520000
0-
#525000
b110 _
b100 G
1-
0*
#530000
0-
#535000
b100 G
1-
#537500
b101 =
b101 O
b101 U
b111 :
b111 C
b111 Z
b101 W
b111 Y
b101 X
b100 L
b101 2
0+
1*
#540000
0-
#545000
b100 G
1-
#550000
0-
0*
#555000
b111 6
b111 F
b111 [
b100 G
1-
#560000
0-
#562500
b10000 #
b10000 <
b10000 S
b101 Y
b110 X
b100 L
1+
1*
#565000
b111 ^
b100 G
1-
#570000
0-
#575000
b111 _
b100 G
1-
0*
#580000
0-
#585000
b100 G
1-
#587500
b110 =
b110 O
b110 U
b101 :
b101 C
b101 Z
b110 W
b101 Y
b110 X
b100 L
b110 2
0+
1*
#590000
0-
#595000
b100 G
1-
#600000
0-
0*
#605000
b101 6
b101 F
b101 [
b100 G
1-
#610000
0-
#612500
b10001 #
b10001 <
b10001 S
b100 Y
b111 X
b100 L
1+
1*
#615000
b101 ^
b100 G
1-
#620000
0-
#625000
b101 _
b100 G
1-
0*
#630000
0-
#635000
b100 G
1-
#637500
b111 =
b111 O
b111 U
b100 :
b100 C
b100 Z
b111 W
b100 Y
b111 X
b100 L
b111 2
0+
1*
#640000
0-
#645000
b100 G
1-
#650000
0-
0*
#655000
b100 6
b100 F
b100 [
b100 G
1-
#660000
0-
#662500
b10010 #
b10010 <
b10010 S
b1100 Y
b1000 X
b100 L
1+
1*
#665000
b100 ^
b100 G
1-
#670000
0-
#675000
b100 _
b100 G
1-
0*
#680000
0-
#685000
b100 G
1-
#687500
b0 =
b0 O
b0 U
b1100 :
b1100 C
b1100 Z
b1000 W
1;
1"
b1100 Y
b1000 X
b100 L
b1000 2
0+
1*
#690000
0-
#695000
b100 G
1-
#700000
0-
0*
#705000
b1100 6
b1100 F
b1100 [
b100 G
1-
#710000
0-
#712500
b100 L
1*
#713500
b0 Y
b0 X
b0 >
b0 K
b0 T
b0 b
b0 a
b0 6
b0 F
b0 [
b0 :
b0 C
b0 Z
b0 W
b0 7
b0 H
b0 c
b0 `
b100 L
b100 G
0,
00
#715000
b0 ^
b100 G
1-
#720000
0-
#725000
b0 _
b100 G
1-
0*
#730000
0-
#735000
b100 G
1-
#737500
b100 L
1,
10
1*
#740000
0-
#745000
b100 G
1-
#750000
0-
0*
#755000
b100 G
1-
#760000
0-
#762500
b100 L
b110011 d
b1 4
b0 2
b0 3
1*
#765000
18
b1 b
b1 a
b100 G
1.
b1 3
b110011 /
b110011 5
b110011 M
1-
#770000
0-
#775000
b1 9
b1 N
b1 \
b1 7
b1 H
b1 c
b1 `
08
b1 b
b1 a
b100 G
b110100 d
b10 4
0.
1-
0*
#780000
0-
#785000
18
b11 b
b10 a
b100 G
1.
b10 3
b110100 /
b110100 5
b110100 M
1-
#787500
b100 L
1*
#790000
0-
#795000
b10 9
b10 N
b10 \
b11 7
b11 H
b11 c
b10 `
08
b11 b
b10 a
b100 G
b110101 d
b11 4
0.
1-
#800000
0-
0*
#805000
18
b10 b
b11 a
b100 G
1.
b11 3
b110101 /
b110101 5
b110101 M
1-
#810000
0-
#812500
b1 >
b1 K
b1 T
b100 L
1*
#815000
b11 9
b11 N
b11 \
b10 7
b10 H
b10 c
b11 `
08
b10 b
b11 a
b100 G
b110110 d
b100 4
0.
1-
#820000
0-
#825000
18
b110 b
b100 a
b100 G
1.
b100 3
b110110 /
b110110 5
b110110 M
1-
0*
#830000
0-
#835000
b100 9
b100 N
b100 \
b110 7
b110 H
b110 c
b100 `
08
b110 b
b100 a
b100 G
b110111 d
b101 4
0.
1-
#837500
b11 >
b11 K
b11 T
0;
0"
b100 L
1*
#840000
0-
#845000
18
b111 b
b101 a
b100 G
1.
b101 3
b110111 /
b110111 5
b110111 M
1-
#850000
0-
0*
#855000
b101 9
b101 N
b101 \
b111 7
b111 H
b111 c
b101 `
08
b111 b
b101 a
b100 G
b111000 d
b110 4
0.
1-
#860000
0-
#862500
b110 >
b110 K
b110 T
b110011 #
b110011 <
b110011 S
b1 Y
b1 X
b100 L
1+
1*
#865000
18
b101 b
b110 a
b100 G
1.
b110 3
b111000 /
b111000 5
b111000 M
1-
#870000
0-
#875000
b110 9
b110 N
b110 \
b101 7
b101 H
b101 c
b110 `
08
b101 b
b110 a
b100 G
b111001 d
b111 4
0.
1-
0*
#880000
0-
#885000
18
b100 b
b111 a
b100 G
1.
b111 3
b111001 /
b111001 5
b111001 M
1-
#887500
b111 >
b111 K
b111 T
b1 =
b1 O
b1 U
b1 :
b1 C
b1 Z
b1 W
b1 Y
b1 X
b100 L
b1 2
0+
1*
#890000
0-
#895000
b111 9
b111 N
b111 \
b100 7
b100 H
b100 c
b111 `
08
b100 b
b111 a
b100 G
b111010 d
b1000 4
0.
1-
#900000
0-
0*
#905000
b1 6
b1 F
b1 [
18
b1100 b
b1000 a
b100 G
1.
b1000 3
b111010 /
b111010 5
b111010 M
1-
#910000
0-
#912500
b101 >
b101 K
b101 T
b110100 #
b110100 <
b110100 S
b11 Y
b10 X
b100 L
1+
1*
#915000
b0 9
b0 N
b0 \
1!
b1100 7
b1100 H
b1100 c
b1000 `
b1 ^
08
b1100 b
b1000 a
b100 G
b1001 4
0.
1-
#920000
0-
#925000
b1 _
b100 G
1-
0*
#930000
0-
#935000
0!
b100 G
1-
#937500
b100 >
b100 K
b100 T
b10 =
b10 O
b10 U
b11 :
b11 C
b11 Z
b10 W
b11 Y
b10 X
b100 L
b10 2
0+
1*
#940000
0-
#945000
b100 G
1-
#950000
0-
0*
#955000
b11 6
b11 F
b11 [
b100 G
1-
#960000
0-
#962500
b1100 >
b1100 K
b1100 T
b110101 #
b110101 <
b110101 S
b10 Y
b11 X
b100 L
1+
1*
#965000
b11 ^
b100 G
1-
#970000
0-
#975000
b11 _
b100 G
1-
0*
#980000
0-
#985000
b100 G
1-
#987500
b11 =
b11 O
b11 U
b10 :
b10 C
b10 Z
b11 W
b10 Y
b11 X
b100 L
b11 2
0+
1*
#990000
0-
#995000
b100 G
1-
#1000000
0-
0*
#1005000
b10 6
b10 F
b10 [
b100 G
1-
#1010000
0-
#1012500
b110110 #
b110110 <
b110110 S
b110 Y
b100 X
b100 L
1+
1*
#1015000
b10 ^
b100 G
1-
#1020000
0-
#1025000
b10 _
b100 G
1-
0*
#1030000
0-
#1035000
b100 G
1-
#1037500
b100 =
b100 O
b100 U
b110 :
b110 C
b110 Z
b100 W
b110 Y
b100 X
b100 L
b100 2
0+
1*
#1040000
0-
#1045000
b100 G
1-
#1050000
0-
0*
#1055000
b110 6
b110 F
b110 [
b100 G
1-
#1060000
0-
#1062500
b110111 #
b110111 <
b110111 S
b111 Y
b101 X
b100 L
1+
1*
#1065000
b110 ^
b100 G
1-
#1070000
0-
