Temsah/Assigments/UART_TX/serializer.v
module serializer
(
//Declaring inputs
    input wire [ 7 : 0 ] P_DATA,
    input wire ser_en,
    input wire CLK,
    input wire RST, //Asynchronus active-low reset

//Declaring outputs
    output reg ser_data,
    output reg ser_done
);
//Declaring a counter to know how many clock cycles are left for the whole data to be fully sent
    reg [ 3 : 0 ] counter;
//Declaring an internal registers to store the parallel data in before we start sending them 
    reg [ 7 : 0 ] internal_reg;
 
    reg busy;

always@( posedge CLK or negedge RST )
    begin
        if( !RST )
            begin
                ser_data <= 1'b1;
                ser_done <= 1'b0;
                internal_reg <= 8'b0;
                counter <= 4'b0;
                busy <= 1'b0;
            end
        else begin
            if( !busy && ser_en)
                begin
                    counter <= 4'b1;          
                    internal_reg <= P_DATA;
                    busy <= 1'b1;
                    ser_done <= 1'b0;
                    ser_data <= P_DATA[0];     
                end   
            else if( busy )
                begin
                    if( counter < 8 )          
                        begin
                            internal_reg <= internal_reg >> 1;
                            ser_data <= internal_reg[1];   
                            counter <= counter + 1;
                            ser_done <= 1'b0;
                        end
                    else // counter == 8
                        begin
                            ser_done <= 1'b1;
                            busy <= 1'b0;
                            ser_data <= 1'b1;   
                        end
                end
            else
                begin
                    ser_data <= 1'b1;         
                end                
        end
    end

endmodule

Temsah/Assigments/UART_TX/serializer_tb.v
`timescale 1ns/1ps
`include "serializer.v"
module serializer_tb;

// Testbench signals
reg [7:0] P_DATA_tb;
reg ser_en_tb;
reg CLK_tb;
reg RST_tb;
wire ser_data_tb;
wire ser_done_tb;

parameter clock_period = 10;

// Instantiate DUT
serializer uut (
    .P_DATA(P_DATA_tb),
    .ser_en(ser_en_tb),
    .CLK(CLK_tb),
    .RST(RST_tb),
    .ser_data(ser_data_tb),
    .ser_done(ser_done_tb)
);

// Clock generation
always begin
    CLK_tb = 1'b0;
    #(clock_period/2);
    CLK_tb = 1'b1;
    #(clock_period/2);
end

// Test logic
initial begin
    $dumpfile("serializer_tb.vcd");
    $dumpvars;

    // Initial state
    P_DATA_tb = 8'b0;
    ser_en_tb = 1'b0;
    RST_tb = 1'b0;

    // Apply reset
    #(2*clock_period);
    RST_tb = 1'b1;
    #(clock_period);

    // Load data
    P_DATA_tb = 8'b10110011; // Expected serial: 1 1 0 0 1 0 1 1
    ser_en_tb = 1'b1;
    #(clock_period);
    ser_en_tb = 1'b0;

    // Monitor serialization output
    repeat (8) begin
        @(posedge CLK_tb);
        $display("Time %0t | ser_data = %b | bit #%0d", $time, ser_data_tb, $time/clock_period - 5);
    end

    // Wait for ser_done
    @(posedge CLK_tb);
    if (ser_done_tb)
        $display("✅ ser_done asserted correctly after 8 bits");
    else
        $display("❌ ser_done not asserted as expected");

    $finish;
end

endmodule

Temsah/Assigments/UART_TX/serializer_tb.vcd
$date
	Thu Aug 07 00:58:26 2025
$end
$version
	Icarus Verilog
$end
$timescale
	1ps
$end
$scope module serializer_tb $end
$var wire 1 ! ser_done_tb $end
$var wire 1 " ser_data_tb $end
$var parameter 32 # clock_period $end
$var reg 1 $ CLK_tb $end
$var reg 8 % P_DATA_tb [7:0] $end
$var reg 1 & RST_tb $end
$var reg 1 ' ser_en_tb $end
$scope module uut $end
$var wire 1 $ CLK $end
$var wire 8 ( P_DATA [7:0] $end
$var wire 1 & RST $end
$var wire 1 ' ser_en $end
$var reg 1 ) busy $end
$var reg 4 * counter [3:0] $end
$var reg 8 + internal_reg [7:0] $end
$var reg 1 " ser_data $end
$var reg 1 ! ser_done $end
$upscope $end
$upscope $end
$enddefinitions $end
$comment Show the parameter values. $end
$dumpall
b1010 #
$end
#0
$dumpvars
b0 +
b0 *
0)
b0 (
0'
0&
b0 %
0$
1"
0!
$end
#5000
1$
#10000
0$
#15000
1$
#20000
0$
1&
#25000
1$
#30000
0$
1'
b10110011 %
b10110011 (
#35000
1)
b10110011 +
1$
#40000
0$
0'
#45000
b1 *
b1011001 +
1$
#50000
0$
#55000
b10 *
b101100 +
1$
#60000
0$
#65000
b11 *
b10110 +
0"
1$
#70000
0$
#75000
b100 *
b1011 +
1$
#80000
0$
#85000
b101 *
b101 +
1"
1$
#90000
0$
#95000
b110 *
b10 +
1$
#100000
0$
#105000
b111 *
b1 +
0"
1$
#110000
0$
#115000
0)
1!
b1000 *
b0 +
1"
1$
