Temsah/Assigments/UP_DOWN_Counter/Up_Dn_Counter.v
module Up_Dn_Counter
(

//Declaring inputs
    input wire [4:0] IN,
    input wire Load,
    input wire Up,
    input wire Down,
    input wire CLK,

//Declaring outputs    
    output reg High,
    output reg [4:0] Counter,
    output reg Low

);

always@(posedge CLK)
    begin

        // Priority: Load > Down > Up
        if(Load==1'b1) 
        Counter<=IN;
        else if( Down==1'b1 && !Low) 
        Counter<=Counter-1;
        else if( Up==1'b1 && !High )
        Counter<=Counter+1;

    end

always@(*)
    begin
        
        if(Counter==5'd31) // Set High flag when Counter reaches 31
        High=1'b1;
        else High=1'b0;

        if(Counter==5'd0) // Set Low flag when Counter reaches 0
        Low=1'b1;
        else Low=1'b0; 

    end

endmodule

Temsah/Assigments/Up_Dn_Counter_tb.v
`timescale 1ns/1ps 
`include "Up_Dn_Counter.v"
module Up_Dn_Counter_tb ();
//Declaring the testbench signals 
     reg [4:0] IN_tb;
     reg Load_tb;
     reg Up_tb;
     reg Down_tb;
     reg CLK_tb;

     wire High_tb;
     wire [4:0] Counter_tb;
     wire Low_tb;


// Design instantiation
Up_Dn_Counter DUT
(

    .IN(IN_tb),
    .Load(Load_tb),
    .Up(Up_tb),
    .Down(Down_tb),
    .CLK(CLK_tb),

    .High(High_tb),
    .Counter(Counter_tb),
    .Low(Low_tb)

);
//clock generation
always #5 CLK_tb=~CLK_tb; //assuming that the frequency of this block is 10Mhz (similar to Lab2)


//Initial block
initial 
    begin
        $dumpfile("Up_Dn_Counter.vcd");
        $dumpvars;
        IN_tb=5'b01010;
        Load_tb=1'b0;
        Up_tb=1'b0;
        Down_tb=1'b0;
        CLK_tb=1'b0;

        $display("Test case 1: "); //testing the latch function
        #10
        Load_tb=1'b1;
        #10
        if(Counter_tb==5'b01010)
            $display ("Test case 1 has passed with counter value = 0x%0h at simulation time=%t",Counter_tb,$time);
        else 
            $display ("Test case 1 has failed with counter value = 0x%0h at simulation time=%t",Counter_tb,$time);

        $display("Test case 2: "); //testing the latch priority (with Up=1)
        #10
         Load_tb=1'b1; Up_tb=1'b1;
         #10
        if(Counter_tb==5'b01010)
            $display ("Test case 2 has passed with counter value = 0x%0h at simulation time=%t",Counter_tb,$time);
        else 
            $display ("Test case 2 has failed with counter value = 0x%0h at simulation time=%t",Counter_tb,$time);

        $display("Test case 3: "); //testing the latch priority (with Down=1)
        #10
         Load_tb=1'b1; Down_tb=1'b1;
        #10
        if(Counter_tb==5'b01010)
            $display ("Test case 3 has passed with counter value = 0x%0h at simulation time=%t",Counter_tb,$time);
        else 
            $display ("Test case 3 has failed with counter value = 0x%0h at simulation time=%t",Counter_tb,$time);


        $display("Test case 4: "); //testing Up functionality
        #10
        Up_tb=1'b1;
        #10
        if(Counter_tb==5'b01011)
            $display ("Test case 4 has passed with counter value = 0x%0h at simulation time=%t",Counter_tb,$time);
        else 
            $display ("Test case 4 has failed with counter value = 0x%0h at simulation time=%t",Counter_tb,$time);

        $display("Test case 5: "); //testing Down priority
        #10
        Up_tb=1'b1; Down_tb=1'b1;
        #10
        if(Counter_tb==5'b01010)
            $display ("Test case 5 has passed with counter value = 0x%0h at simulation time=%t",Counter_tb,$time);
        else 
            $display ("Test case 5 has failed with counter value = 0x%0h at simulation time=%t",Counter_tb,$time);

        $display("Test case 6: "); //testing High flag
        #10
        Up_tb=1'b1;
        Load_tb=1'b1;
        IN_tb=5'b11111;
        #10
        if(Counter_tb==5'b11111)
            $display ("Test case 6 has passed with Low flag value = %0b at simulation time=%t",High_tb,$time);
        else 
            $display ("Test case 6 has failed with Low flag value = %0b at simulation time=%t",High_tb,$time);


        $display("Test case 7: "); //testing Low flag
        #10
        Up_tb=1'b1;
        Load_tb=1'b1;
        IN_tb=5'b00000;
        #10
        if(Counter_tb==5'b00000)
            $display ("Test case 7 has passed with High flag value = %0b at simulation time=%t",Low_tb,$time);
        else 
            $display ("Test case 7 has failed with High flag value = %0b at simulation time=%t",Low_tb,$time);

        $finish;

    end

endmodule

Temsah/Assigments/Up_Dn_Counter.vcd
$date
	Mon Jul 14 17:45:05 2025
$end
$version
	Icarus Verilog
$end
$timescale
	1ps
$end
$scope module Up_Dn_Counter_tb $end
$var wire 1 ! Low_tb $end
$var wire 1 " High_tb $end
$var wire 5 # Counter_tb [4:0] $end
$var reg 1 $ CLK_tb $end
$var reg 1 % Down_tb $end
$var reg 5 & IN_tb [4:0] $end
$var reg 1 ' Load_tb $end
$var reg 1 ( Up_tb $end
$scope module DUT $end
$var wire 1 $ CLK $end
$var wire 1 % Down $end
$var wire 5 ) IN [4:0] $end
$var wire 1 ' Load $end
$var wire 1 ( Up $end
$var reg 5 * Counter [4:0] $end
$var reg 1 " High $end
$var reg 1 ! Low $end
$upscope $end
$upscope $end
$enddefinitions $end
$comment Show the parameter values. $end
$dumpall
$end
#0
$dumpvars
bx *
b1010 )
0(
0'
b1010 &
0%
0$
bx #
x"
x!
$end
#5000
1$
#10000
0$
1'
#15000
0!
0"
b1010 #
b1010 *
1$
#20000
0$
#25000
1$
#30000
0$
1(
#35000
1$
#40000
0$
#45000
1$
#50000
0$
1%
#55000
1$
#60000
0$
#65000
1$
#70000
0$
#75000
1$
#80000
0$
#85000
1$
#90000
0$
#95000
1$
#100000
0$
#105000
1$
#110000
0$
b11111 &
b11111 )
#115000
1"
b11111 #
b11111 *
1$
#120000
0$
#125000
1$
#130000
0$
b0 &
b0 )
#135000
1!
0"
b0 #
b0 *
1$
